{
  "logNo": "223875626500",
  "url": "https://m.blog.naver.com/jumbocard/223875626500",
  "title": "여름 일본 홋카이도 해외 여행 사진 명소 포토북으로 만들기",
  "category": "점보 팁",
  "content_html": "<div class=\"se-component se-sticker se-l-default\" id=\"SE-d87ab3ad-4909-40fc-8f22-329664e56c73\">\n<div class=\"se-component-content\">\n<div class=\"se-section se-section-sticker se-section-align-center se-l-default\">\n<div class=\"se-module se-module-sticker\">\n<a class=\"__se_sticker_link __se_link\" data-linkdata='{\"src\" : \"https://storep-phinf.pstatic.net/motion2d_01/original_7.png\", \"packCode\" : \"motion2d_01\", \"seq\" : \"7\", \"width\" : \"185\", \"height\" : \"160\"}' data-linktype=\"sticker\" href=\"#\" onclick=\"return false;\">\n<img alt=\"\" class=\"se-sticker-image\" src=\"https://storep-phinf.pstatic.net/motion2d_01/original_7.png?type=p100_100\"/>\n</a>\n</div>\n</div>\n</div>\n</div> <div class=\"se-component se-quotation se-l-default\" id=\"SE-5b1d1617-a3da-4802-880a-c34730cf948a\">\n<div class=\"se-component-content\">\n<div class=\"se-section se-section-quotation se-l-default\">\n<blockquote class=\"se-quotation-container\">\n<div class=\"se-module se-module-text se-quote\"><!-- SE-TEXT { --><p class=\"se-text-paragraph se-text-paragraph-align-\" id=\"SE-ea120280-8a3e-4881-af29-e765e82f9cd6\" style=\"\"><span class=\"se-fs- se-ff-\" id=\"SE-02898c21-b29c-48dd-8889-1c3f0ceb6871\" style=\"color:#000000;\"><b>홋카이도는 삿포로의 라벤더 축제, 맥주축제, 불꽃놀이 같은 다채로운 여름 이벤트부터</b></span></p><!-- } SE-TEXT --><!-- SE-TEXT { --><p class=\"se-text-paragraph se-text-paragraph-align-\" id=\"SE-7b412bce-e880-4895-ad5a-3f1503a37e07\" style=\"\"><span class=\"se-fs- se-ff-\" id=\"SE-ee07b6b2-7dd9-4250-9116-aa44fe16cd6b\" style=\"color:#000000;\"><b>광활한 자연 풍경까지 모두 즐길 수 있는 멋진 곳입니다.</b></span></p><!-- } SE-TEXT --></div>\n</blockquote>\n</div>\n</div>\n</div>\n<div class=\"se-component se-image se-l-default\" id=\"SE-dcce8abf-b242-4932-8c74-19cf97875093\">\n<div class=\"se-component-content se-component-content-fit\">\n<div class=\"se-section se-section-image se-l-default se-section-align-justify\">\n<div class=\"se-module se-module-image\" style=\"\">\n<a class=\"se-module-image-link __se_image_link __se_link\" data-linkdata='{\"id\" : \"SE-dcce8abf-b242-4932-8c74-19cf97875093\", \"src\" : \"https://mblogthumb-phinf.pstatic.net/MjAyNTA1MjNfMTM2/MDAxNzQ3OTk0NDY4MjEz.XVNjwHvSR2Wr8AMLlT-bC7FEIZ6iLcxMh-TPtDZBRrcg.cNQhuleUYvqeTCHt2TytQBj2ULMGQOEuWZp2saNPEn0g.PNG/001.png\", \"originalWidth\" : \"1080\", \"originalHeight\" : \"1080\", \"linkUse\" : \"false\", \"link\" : \"\"}' data-linktype=\"img\" href=\"#\" onclick=\"return false;\" style=\"\">\n<img alt=\"\" class=\"se-image-resource\" src=\"https://mblogthumb-phinf.pstatic.net/MjAyNTA1MjNfMTM2/MDAxNzQ3OTk0NDY4MjEz.XVNjwHvSR2Wr8AMLlT-bC7FEIZ6iLcxMh-TPtDZBRrcg.cNQhuleUYvqeTCHt2TytQBj2ULMGQOEuWZp2saNPEn0g.PNG/001.png?type=w966\"/>\n</a>\n</div>\n</div>\n</div>\n\n</div>\n<div class=\"se-component se-text se-l-default\" id=\"SE-557ce304-9e19-4e45-92c5-592c2665a7c8\">\n<div class=\"se-component-content\">\n<div class=\"se-section se-section-text se-l-default\">\n<div class=\"se-module se-module-text\">\n<!-- SE-TEXT { --><p class=\"se-text-paragraph se-text-paragraph-align-justify\" id=\"SE-cfe6b8d3-8476-4b68-b03f-5dd060b68ca1\" style=\"line-height:1.9;\"><span class=\"se-fs-fs19 se-ff-nanumsquare\" id=\"SE-c4d3eb9e-3fb2-4f3e-b87a-d18fd08ab960\" style=\"color:#000000;\">​</span></p><!-- } SE-TEXT --><!-- SE-TEXT { --><p class=\"se-text-paragraph se-text-paragraph-align-justify\" id=\"SE-3f62e738-a525-42bb-bb03-49ac497bb09e\" style=\"line-height:1.9;\"><span class=\"se-fs-fs19 se-ff-nanumsquare se-weight-unset se-style-unset\" id=\"SE-3eae5955-4898-4e4c-9f18-9d514451b920\" style=\"color:#000000;\">우리나라와 다르게 일본 홋카이도는 7~8월 평균 기온이 20도 초반으로 유지되는데요. 그래서 </span><span class=\"se-fs-fs19 se-ff-nanumsquare se-weight-unset\" id=\"SE-516adf09-b234-4cac-8b6c-8d56a12ded71\" style=\"color:#000000;\"><i>한여름에도 선선한 날씨를 즐길 수 있는 대표적인 해외여행지</i></span><span class=\"se-fs-fs19 se-ff-nanumsquare se-weight-unset se-style-unset\" id=\"SE-775c00a6-2851-4534-9f32-5f9c9bc73c35\" style=\"color:#000000;\">이죠. </span></p><!-- } SE-TEXT --><!-- SE-TEXT { --><p class=\"se-text-paragraph se-text-paragraph-align-justify\" id=\"SE-935a7d2f-c9b9-48f7-8ac0-3c02aad35e47\" style=\"line-height:1.9;\"><span class=\"se-fs-fs19 se-ff-nanumsquare\" id=\"SE-cf87f6a2-baf7-44b0-9527-063c27186207\" style=\"color:#000000;\"><i><b>​</b></i></span></p><!-- } SE-TEXT --><!-- SE-TEXT { --><p class=\"se-text-paragraph se-text-paragraph-align-justify\" id=\"SE-4e6574a2-94c1-4083-ab11-b51e33ffc639\" style=\"line-height:1.9;\"><span class=\"se-fs-fs19 se-ff-nanumsquare\" id=\"SE-92beb2ee-8ac1-40d9-8753-fec2e768ec18\" style=\"color:#000000;\">후라노 라벤더 밭, 청의 호수, 샤코탄 해안처럼 여름에 사진 찍기 좋은 장소도 많아 여행지로서 만족도가 높은데요. 이렇게 남긴 사진을 어떻게 정리하느냐에 따라 여행의 기억이 더 오래 남기도 하죠.</span></p><!-- } SE-TEXT --><!-- SE-TEXT { --><p class=\"se-text-paragraph se-text-paragraph-align-justify\" id=\"SE-58fb2a5d-efdb-4853-b466-b10a65535018\" style=\"line-height:1.9;\"><span class=\"se-fs-fs19 se-ff-nanumsquare\" id=\"SE-e61b160c-539e-430a-9494-f98b1084c932\" style=\"color:#000000;\"> </span></p><!-- } SE-TEXT --><!-- SE-TEXT { --><p class=\"se-text-paragraph se-text-paragraph-align-justify\" id=\"SE-1e8d1ec9-e64b-4235-844b-50f5d68ffa3d\" style=\"line-height:1.9;\"><span class=\"se-fs-fs19 se-ff-nanumsquare\" id=\"SE-f1730094-a594-459b-b12e-304a6e11ef76\" style=\"color:#000000;\"><u>이번 글에서는 여름 홋카이도의 감성적인 포토 스팟부터 여행 사진을 더욱 특별하게 남기는 방법까지 함께 살펴보겠습니다.</u></span></p><!-- } SE-TEXT --><!-- SE-TEXT { --><p class=\"se-text-paragraph se-text-paragraph-align-justify\" id=\"SE-ac943e41-1c37-44b1-914f-214a53dc81c2\" style=\"line-height:1.9;\"><span class=\"se-fs-fs19 se-ff-nanumsquare\" id=\"SE-100fdedf-6cfa-45b0-bf18-4396d40aab6e\" style=\"color:#000000;\"> </span></p><!-- } SE-TEXT -->\n</div>\n</div>\n</div>\n\n</div> <div class=\"se-component se-quotation se-l-quotation_underline\" id=\"SE-aba32a11-8bdd-4241-a91c-c3bcd95e9095\">\n<div class=\"se-component-content\">\n<div class=\"se-section se-section-quotation se-l-quotation_underline\">\n<blockquote class=\"se-quotation-container\">\n<div class=\"se-module se-module-text se-quote\"><!-- SE-TEXT { --><p class=\"se-text-paragraph se-text-paragraph-align-\" id=\"SE-13ba283f-e94a-49b4-afbb-a3adf62f257e\" style=\"\"><span class=\"se-fs-fs24 se-ff-\" id=\"SE-bd090354-fc39-4c54-a062-c904d4e525fb\" style=\"color:#000000;\"><b>SNS에서 핫한 홋카이도 감성 사진 명소는?</b></span></p><!-- } SE-TEXT --></div>\n</blockquote>\n</div>\n</div>\n</div>\n<div class=\"se-component se-text se-l-default\" id=\"SE-d40acb0c-5e4f-442c-ab23-dc7b44155b74\">\n<div class=\"se-component-content\">\n<div class=\"se-section se-section-text se-l-default\">\n<div class=\"se-module se-module-text\">\n<!-- SE-TEXT { --><p class=\"se-text-paragraph se-text-paragraph-align-justify\" id=\"SE-a5ae7378-3643-4f0c-abfd-d7aefd10d24d\" style=\"line-height:1.9;\"><span class=\"se-fs-fs19 se-ff-nanumsquare\" id=\"SE-21d78370-b88c-4c1a-8493-ba4794d6fb78\" style=\"color:#000000;\">여름 홋카이도는 어디를 가도 그림이 되지만, 그중에서도 사진 애호가들 사이에서 특히 인기가 많은 세 곳이 있습니다. 인생 샷을 남기고 싶은 분이라면 이 세 곳은 꼭 들러보세요.</span></p><!-- } SE-TEXT --><!-- SE-TEXT { --><p class=\"se-text-paragraph se-text-paragraph-align-justify\" id=\"SE-e1e37d03-b9e4-473e-96e6-d3861a48db2c\" style=\"line-height:1.9;\"><span class=\"se-fs-fs19 se-ff-nanumsquare\" id=\"SE-d1ba469d-c87f-418b-aff4-e239266e45d4\" style=\"color:#000000;\"> </span></p><!-- } SE-TEXT -->\n</div>\n</div>\n</div>\n\n</div> <div class=\"se-component se-quotation se-l-quotation_line\" id=\"SE-0651a42b-6a83-42a4-ad0c-32ce3bee5a99\">\n<div class=\"se-component-content\">\n<div class=\"se-section se-section-quotation se-l-quotation_line\">\n<blockquote class=\"se-quotation-container\">\n<div class=\"se-module se-module-text se-quote\"><!-- SE-TEXT { --><p class=\"se-text-paragraph se-text-paragraph-align-\" id=\"SE-4d50baa3-ae83-4239-b1dd-aea942400467\" style=\"\"><span class=\"se-fs-fs24 se-ff-\" id=\"SE-c9c360ad-2d88-43e1-9435-b6ddecd1c858\" style=\"color:#000000;\"><b>① 후라노 팜 토미타 – 북해도의 라벤더 천국</b></span></p><!-- } SE-TEXT --></div>\n</blockquote>\n</div>\n</div>\n</div>\n<div class=\"se-component se-image se-l-default\" id=\"SE-0f5f851e-f740-4f40-898c-b80faa7bbbed\">\n<div class=\"se-component-content se-component-content-fit\">\n<div class=\"se-section se-section-image se-l-default se-section-align-justify\">\n<div class=\"se-module se-module-image\" style=\"\">\n<a class=\"se-module-image-link __se_image_link __se_link\" data-linkdata='{\"id\" : \"SE-0f5f851e-f740-4f40-898c-b80faa7bbbed\", \"src\" : \"https://mblogthumb-phinf.pstatic.net/MjAyNTA1MjNfNTYg/MDAxNzQ3OTk0NTA2MzU4.Mlty0tk1HnghKfCeFIFUnhvEE55zzJey6r4ghtNDeBgg.35irNVUkegraLp4KN1DBITVNNNvO3MDzjnm-JjAqlLkg.PNG/002.png\", \"originalWidth\" : \"1080\", \"originalHeight\" : \"1080\", \"linkUse\" : \"false\", \"link\" : \"\"}' data-linktype=\"img\" href=\"#\" onclick=\"return false;\" style=\"\">\n<img alt=\"\" class=\"se-image-resource\" src=\"https://mblogthumb-phinf.pstatic.net/MjAyNTA1MjNfNTYg/MDAxNzQ3OTk0NTA2MzU4.Mlty0tk1HnghKfCeFIFUnhvEE55zzJey6r4ghtNDeBgg.35irNVUkegraLp4KN1DBITVNNNvO3MDzjnm-JjAqlLkg.PNG/002.png?type=w966\"/>\n</a>\n</div>\n</div>\n</div>\n\n</div>\n<div class=\"se-component se-text se-l-default\" id=\"SE-818f9d60-4dc8-4700-874e-bdadc33bbbcb\">\n<div class=\"se-component-content\">\n<div class=\"se-section se-section-text se-l-default\">\n<div class=\"se-module se-module-text\">\n<!-- SE-TEXT { --><p class=\"se-text-paragraph se-text-paragraph-align-justify\" id=\"SE-b8b58cab-9e8c-45dc-bc0a-918a3d16cc64\" style=\"line-height:1.9;\"><span class=\"se-fs-fs19 se-ff-nanumsquare\" id=\"SE-83850c6c-cf31-4de2-be22-8602c8c347cb\" style=\"color:#000000;\"> </span></p><!-- } SE-TEXT --><!-- SE-TEXT { --><p class=\"se-text-paragraph se-text-paragraph-align-justify se-text-paragraph-drop-cap\" id=\"SE-96d850d3-9bf9-4b35-b1af-97e2c78f435e\" style=\"line-height:1.9;\"><span class=\"se-fs-fs19 se-ff-nanumsquare\" id=\"SE-321956de-0b5d-41ac-a2c6-14e541077462\" style=\"color:#000000;\"><i><span class=\"se-drop-cap\">여</span>름 홋카이도 하면 가장 먼저 떠오르는 풍경이 바로 </i></span><span class=\"se-fs-fs24 se-ff-nanumsquare\" id=\"SE-5585617c-a61f-4e49-a6c5-bc65266561d9\" style=\"color:#000000;\"><i><b>라벤더</b></i></span><span class=\"se-fs-fs19 se-ff-nanumsquare\" id=\"SE-1df95677-7139-4cd4-baca-bdfa43f9fa19\" style=\"color:#000000;\"><i>입니다. </i></span><span class=\"se-fs-fs19 se-ff-nanumsquare\" id=\"SE-7ffaad8d-8a7f-401c-8484-05c381571d48\" style=\"color:#000000;\">홋카이도 중부에 위치한 후라노는 여름 라벤더 시즌의 중심지인데요.</span></p><!-- } SE-TEXT --><!-- SE-TEXT { --><p class=\"se-text-paragraph se-text-paragraph-align-justify\" id=\"SE-02a5f303-8d11-4351-9292-2b16dcc1fb4b\" style=\"line-height:1.9;\"><span class=\"se-fs-fs19 se-ff-nanumsquare\" id=\"SE-df055e84-8301-4fed-b986-b74ee913f96b\" style=\"color:#000000;\"> </span></p><!-- } SE-TEXT --><!-- SE-TEXT { --><p class=\"se-text-paragraph se-text-paragraph-align-justify\" id=\"SE-a49bee88-2249-4fce-a241-84ba8c0fd615\" style=\"line-height:1.9;\"><span class=\"se-fs-fs19 se-ff-nanumsquare\" id=\"SE-4203f903-4c00-426e-9576-e9cf9e93f4f2\" style=\"color:#000000;\">그 중심에는 ‘</span><span class=\"se-fs-fs24 se-ff-nanumsquare\" id=\"SE-8ca11aec-efe8-4590-86d7-ac236d5d8db0\" style=\"color:#000000;\"><b>팜 토미타(Farm Tomita)’</b></span><span class=\"se-fs-fs19 se-ff-nanumsquare\" id=\"SE-a03e0d69-0d94-4f53-858b-0d861e92bd80\" style=\"color:#000000;\">가 있죠. 북해도에서도 넓은 라벤더 밭을 자랑하고 있는 만큼, 보랏빛 향연이 펼쳐지는 정원 같은 공간입니다. 라벤더 향이 솔솔 퍼지는 가운데 사진을 찍으면, 배경은 물론 향기까지 담긴 듯한 느낌을 받을 수 있어요. </span></p><!-- } SE-TEXT --><!-- SE-TEXT { --><p class=\"se-text-paragraph se-text-paragraph-align-justify\" id=\"SE-996304d7-382f-422c-9d9f-9ac90ee6cd4a\" style=\"line-height:1.9;\"><span class=\"se-fs-fs19 se-ff-nanumsquare\" id=\"SE-61f5b7c1-0ef2-4d5c-9813-203ae4d90195\" style=\"color:#000000;\">​</span></p><!-- } SE-TEXT --><!-- SE-TEXT { --><p class=\"se-text-paragraph se-text-paragraph-align-justify\" id=\"SE-3caa090b-37d0-4ff4-a57f-b9a67b647b00\" style=\"line-height:1.9;\"><span class=\"se-fs-fs19 se-ff-nanumsquare\" id=\"SE-22d8d10f-eb37-4e84-ae92-9f8cbaa08de4\" style=\"color:#000000;\">팜 토미타는 라벤더 외에도 다양한 계절 꽃들이 가득한 꽃밭으로도 유명한데요. 아이스크림 가게나 기념품 숍 등 작은 즐거움도 함께할 수 있는 여행지입니다.</span></p><!-- } SE-TEXT --><!-- SE-TEXT { --><p class=\"se-text-paragraph se-text-paragraph-align-justify\" id=\"SE-692f9629-d958-4de5-b4a6-c24f20e593e6\" style=\"line-height:1.9;\"><span class=\"se-fs-fs19 se-ff-nanumsquare\" id=\"SE-55f81db7-6e21-4418-8a5e-79a5f3027038\" style=\"color:#000000;\"> </span></p><!-- } SE-TEXT -->\n</div>\n</div>\n</div>\n\n</div> <div class=\"se-component se-quotation se-l-quotation_line\" id=\"SE-12ce48fb-e238-4344-859c-b8675b57041b\">\n<div class=\"se-component-content\">\n<div class=\"se-section se-section-quotation se-l-quotation_line\">\n<blockquote class=\"se-quotation-container\">\n<div class=\"se-module se-module-text se-quote\"><!-- SE-TEXT { --><p class=\"se-text-paragraph se-text-paragraph-align-\" id=\"SE-bc37d6e4-587e-4875-a09d-3c1a0e1459bd\" style=\"\"><span class=\"se-fs-fs24 se-ff-\" id=\"SE-f2f4e61b-a6d7-406a-b899-c7788dc96584\" style=\"color:#000000;\"><b>② 비에이 시로가네 아오이이케(청의 호수) &amp; 흰수염 폭포</b></span></p><!-- } SE-TEXT --></div>\n</blockquote>\n</div>\n</div>\n</div>\n<div class=\"se-component se-image se-l-default\" id=\"SE-bbf4fc54-f58c-47d5-be8b-9089bf0a29bc\">\n<div class=\"se-component-content se-component-content-fit\">\n<div class=\"se-section se-section-image se-l-default se-section-align-justify\">\n<div class=\"se-module se-module-image\" style=\"\">\n<a class=\"se-module-image-link __se_image_link __se_link\" data-linkdata='{\"id\" : \"SE-bbf4fc54-f58c-47d5-be8b-9089bf0a29bc\", \"src\" : \"https://mblogthumb-phinf.pstatic.net/MjAyNTA1MjNfMjIz/MDAxNzQ3OTk0NTA5MTk0.hdoY3ehEs8BbEm1w3vDITW8odbRIWPGMQv9K3GDIh4Qg.9_YFbJfkLukWmP-am9mhKINQFblcxeina9fVpdXkwvAg.PNG/003.png\", \"originalWidth\" : \"1080\", \"originalHeight\" : \"1080\", \"linkUse\" : \"false\", \"link\" : \"\"}' data-linktype=\"img\" href=\"#\" onclick=\"return false;\" style=\"\">\n<img alt=\"\" class=\"se-image-resource\" src=\"https://mblogthumb-phinf.pstatic.net/MjAyNTA1MjNfMjIz/MDAxNzQ3OTk0NTA5MTk0.hdoY3ehEs8BbEm1w3vDITW8odbRIWPGMQv9K3GDIh4Qg.9_YFbJfkLukWmP-am9mhKINQFblcxeina9fVpdXkwvAg.PNG/003.png?type=w966\"/>\n</a>\n</div>\n</div>\n</div>\n\n</div>\n<div class=\"se-component se-text se-l-default\" id=\"SE-90f18953-c371-4352-97d8-35c539ffaa3a\">\n<div class=\"se-component-content\">\n<div class=\"se-section se-section-text se-l-default\">\n<div class=\"se-module se-module-text\">\n<!-- SE-TEXT { --><p class=\"se-text-paragraph se-text-paragraph-align-justify\" id=\"SE-946dab1b-8f10-4706-8de2-053f9b38c909\" style=\"line-height:1.9;\"><span class=\"se-fs-fs19 se-ff-nanumsquare\" id=\"SE-52d7f1ab-5439-40d3-8509-fefe11e79c40\" style=\"color:#000000;\"> </span></p><!-- } SE-TEXT --><!-- SE-TEXT { --><p class=\"se-text-paragraph se-text-paragraph-align-justify se-text-paragraph-drop-cap\" id=\"SE-aac6e0d8-c097-4e3d-8d0f-6f20260b3d5c\" style=\"line-height:1.9;\"><span class=\"se-fs-fs19 se-ff-nanumsquare\" id=\"SE-eeb0700e-a7db-4daa-92eb-234c4f92a683\" style=\"color:#000000;\"><i><span class=\"se-drop-cap\">비</span>에이는 후라노에서 북쪽 방향으로 JR 비에이역에서 차로 약 30분 거리</i></span><span class=\"se-fs-fs19 se-ff-nanumsquare\" id=\"SE-0aa7db9d-a9c9-4684-a85c-4c19ab8e34b0\" style=\"color:#000000;\">에 있으며, </span><span class=\"se-fs-fs19 se-ff-nanumsquare\" id=\"SE-e821a4ba-aab0-4bcf-8550-6029d19b51d3\" style=\"color:#000000;\"><b>청의 호수와 흰수염 폭포는 서로 인접한 명소로 함께 방문하기에 좋습니다.</b></span></p><!-- } SE-TEXT --><!-- SE-TEXT { --><p class=\"se-text-paragraph se-text-paragraph-align-justify\" id=\"SE-57370f01-1663-43a8-9465-174e1a0977f5\" style=\"line-height:1.9;\"><span class=\"se-fs-fs19 se-ff-nanumsquare\" id=\"SE-b491b038-db0b-4fb8-82a3-44be6de65888\" style=\"color:#000000;\"> </span></p><!-- } SE-TEXT --><!-- SE-TEXT { --><p class=\"se-text-paragraph se-text-paragraph-align-justify\" id=\"SE-a1fe10ee-3030-450f-87f9-8f3a4bfbf8b0\" style=\"line-height:1.9;\"><span class=\"se-fs-fs19 se-ff-nanumsquare\" id=\"SE-567dddee-0622-4f6b-815a-1918442146db\" style=\"color:#000000;\">자연이 만들어낸 마법 같은 풍경을 경험하고 싶다면, 청의 호수(시로가네 아오이이케)와 흰수염 폭포를 빼놓을 수 없습니다. </span><span class=\"se-fs-fs24 se-ff-nanumsquare\" id=\"SE-3232b50f-d8a8-41fa-8225-c92e4c485fc4\" style=\"color:#000000;\"><i><b>청의 호수</b></i></span><span class=\"se-fs-fs19 se-ff-nanumsquare\" id=\"SE-dd864f71-5140-48bc-8231-932285221f0b\" style=\"color:#000000;\"><i><b>는 푸르른빛이 그대로 스며든 듯한 수면과, 그 위에 비친 자작나무 그림자가 인상적인 곳</b></i></span><span class=\"se-fs-fs19 se-ff-nanumsquare\" id=\"SE-4b7974f2-b31f-4742-814c-017464a71331\" style=\"color:#000000;\">이에요. 카메라 셔터만 누르면 누구나 신비로운 반영 사진을 얻을 수 있는 명소로 유명합니다.</span></p><!-- } SE-TEXT --><!-- SE-TEXT { --><p class=\"se-text-paragraph se-text-paragraph-align-justify\" id=\"SE-93c1dcf1-ef7d-44e8-acf7-14e81356c8a8\" style=\"line-height:1.9;\"><span class=\"se-fs-fs19 se-ff-nanumsquare\" id=\"SE-0036b8f5-cb3e-4cc2-a500-379b478cdd33\" style=\"color:#000000;\"> </span></p><!-- } SE-TEXT -->\n</div>\n</div>\n</div>\n\n</div> <div class=\"se-component se-image se-l-default\" id=\"SE-cecb072a-63c7-412b-8e15-4b697e6bae22\">\n<div class=\"se-component-content se-component-content-fit\">\n<div class=\"se-section se-section-image se-l-default se-section-align-justify\">\n<div class=\"se-module se-module-image\" style=\"\">\n<a class=\"se-module-image-link __se_image_link __se_link\" data-linkdata='{\"id\" : \"SE-cecb072a-63c7-412b-8e15-4b697e6bae22\", \"src\" : \"https://mblogthumb-phinf.pstatic.net/MjAyNTA1MjNfNjEg/MDAxNzQ3OTk0NTEyNTY1.8Ivg9MAkz45IC4NzvgmKbaSh0GmmVppa4YoN1eFjWSQg.rnIYxfrqBBqmzze4PCeq56uglmTiJeNHfJOGmxblHT4g.PNG/004.png\", \"originalWidth\" : \"1080\", \"originalHeight\" : \"1080\", \"linkUse\" : \"false\", \"link\" : \"\"}' data-linktype=\"img\" href=\"#\" onclick=\"return false;\" style=\"\">\n<img alt=\"\" class=\"se-image-resource\" src=\"https://mblogthumb-phinf.pstatic.net/MjAyNTA1MjNfNjEg/MDAxNzQ3OTk0NTEyNTY1.8Ivg9MAkz45IC4NzvgmKbaSh0GmmVppa4YoN1eFjWSQg.rnIYxfrqBBqmzze4PCeq56uglmTiJeNHfJOGmxblHT4g.PNG/004.png?type=w966\"/>\n</a>\n</div>\n</div>\n</div>\n\n</div>\n<div class=\"se-component se-text se-l-default\" id=\"SE-b6d06266-3536-4b8d-a084-e690cc1eb2ed\">\n<div class=\"se-component-content\">\n<div class=\"se-section se-section-text se-l-default\">\n<div class=\"se-module se-module-text\">\n<!-- SE-TEXT { --><p class=\"se-text-paragraph se-text-paragraph-align-justify\" id=\"SE-767d1f26-bf9f-49ef-8f5e-9017bf3057a1\" style=\"line-height:1.9;\"><span class=\"se-fs-fs19 se-ff-nanumsquare\" id=\"SE-28957073-6000-44ca-a386-edbbef487d0e\" style=\"color:#000000;\"> </span></p><!-- } SE-TEXT --><!-- SE-TEXT { --><p class=\"se-text-paragraph se-text-paragraph-align-justify\" id=\"SE-1c690548-4b54-4aa5-83ad-e1a38b67abb6\" style=\"line-height:1.9;\"><span class=\"se-fs-fs19 se-ff-nanumsquare\" id=\"SE-263c0852-4984-4081-b985-672065f407d1\" style=\"color:#000000;\">바로 근처에 위치한</span><span class=\"se-fs-fs24 se-ff-nanumsquare\" id=\"SE-c2ced0a3-912b-47a2-953f-5db61d0bbd49\" style=\"color:#000000;\"><i><b> 흰 수염 폭포</b></i></span><span class=\"se-fs-fs19 se-ff-nanumsquare\" id=\"SE-da439a15-de18-4180-91ea-f2c3b75ebec3\" style=\"color:#000000;\"><i><b>는 용암층 사이로 흘러내리는 물줄기가 마치 ‘하얀 수염’처럼 흩어져 내려와, 청록빛 강과 조화를 이루며 이색적인 풍경</b></i></span><span class=\"se-fs-fs19 se-ff-nanumsquare\" id=\"SE-f9834ce8-21a3-43ca-bcfc-c27ca7bf3765\" style=\"color:#000000;\">을 보여주는 데요. 특히 여기는 햇빛이 강할수록 색감이 더욱 깊어지기 때문에 오전 10시부터 오후 2시 사이에 방문하시면 더 아름다운 장면을 담을 수 있어요.</span></p><!-- } SE-TEXT --><!-- SE-TEXT { --><p class=\"se-text-paragraph se-text-paragraph-align-justify\" id=\"SE-822061df-5115-4ddf-87e4-7f2ac842b06a\" style=\"line-height:1.9;\"><span class=\"se-fs-fs19 se-ff-nanumsquare\" id=\"SE-c0443cab-16ef-4770-8604-b4e3b70379d8\" style=\"color:#000000;\"> </span></p><!-- } SE-TEXT -->\n</div>\n</div>\n</div>\n\n</div> <div class=\"se-component se-quotation se-l-quotation_line\" id=\"SE-72ba74e7-ccff-4a2f-91bc-c1c03f6055b4\">\n<div class=\"se-component-content\">\n<div class=\"se-section se-section-quotation se-l-quotation_line\">\n<blockquote class=\"se-quotation-container\">\n<div class=\"se-module se-module-text se-quote\"><!-- SE-TEXT { --><p class=\"se-text-paragraph se-text-paragraph-align-\" id=\"SE-5f421b65-b672-4030-a12d-372551a41f8e\" style=\"\"><span class=\"se-fs-fs24 se-ff-\" id=\"SE-58c848ec-eced-4543-a2f4-f9dedff33516\" style=\"color:#000000;\"><b>③ 샤코탄 반도 시마무이 해안 &amp; 카무이미사키</b></span></p><!-- } SE-TEXT --></div>\n</blockquote>\n</div>\n</div>\n</div>\n<div class=\"se-component se-image se-l-default\" id=\"SE-8184ede6-57f9-440e-a698-70a7b0049efc\">\n<div class=\"se-component-content se-component-content-fit\">\n<div class=\"se-section se-section-image se-l-default se-section-align-justify\">\n<div class=\"se-module se-module-image\" style=\"\">\n<a class=\"se-module-image-link __se_image_link __se_link\" data-linkdata='{\"id\" : \"SE-8184ede6-57f9-440e-a698-70a7b0049efc\", \"src\" : \"https://mblogthumb-phinf.pstatic.net/MjAyNTA1MjNfMzUg/MDAxNzQ3OTk0NTE3ODk4.9xvPv-NPK5_Q6_kWyYtClT2Y2kgsCfcJ1eaMu5SLD_Eg.ISq-vWIup8kCoCwmlV4xdGqlPGCy_6_8SkR5bK5baAsg.PNG/005.png\", \"originalWidth\" : \"1080\", \"originalHeight\" : \"1080\", \"linkUse\" : \"false\", \"link\" : \"\"}' data-linktype=\"img\" href=\"#\" onclick=\"return false;\" style=\"\">\n<img alt=\"\" class=\"se-image-resource\" src=\"https://mblogthumb-phinf.pstatic.net/MjAyNTA1MjNfMzUg/MDAxNzQ3OTk0NTE3ODk4.9xvPv-NPK5_Q6_kWyYtClT2Y2kgsCfcJ1eaMu5SLD_Eg.ISq-vWIup8kCoCwmlV4xdGqlPGCy_6_8SkR5bK5baAsg.PNG/005.png?type=w966\"/>\n</a>\n</div>\n</div>\n</div>\n\n</div>\n<div class=\"se-component se-text se-l-default\" id=\"SE-f08c0039-c2b5-4743-85a3-baa46bb58218\">\n<div class=\"se-component-content\">\n<div class=\"se-section se-section-text se-l-default\">\n<div class=\"se-module se-module-text\">\n<!-- SE-TEXT { --><p class=\"se-text-paragraph se-text-paragraph-align-justify\" id=\"SE-d4c06358-0da6-4269-a9df-d4672f5c832e\" style=\"line-height:1.9;\"><span class=\"se-fs-fs19 se-ff-nanumsquare\" id=\"SE-b558c12e-9bdc-421e-ad4e-42a86bb5f26a\" style=\"color:#000000;\"> </span></p><!-- } SE-TEXT --><!-- SE-TEXT { --><p class=\"se-text-paragraph se-text-paragraph-align-justify\" id=\"SE-10e1ec8b-8a60-4a05-ac67-87fa2f657a8c\" style=\"line-height:1.9;\"><span class=\"se-fs-fs19 se-ff-nanumsquare\" id=\"SE-9bdb3109-5135-49df-98c4-41a083bda7e3\" style=\"color:#000000;\"><i><b>오타루에서 차로 약 1시간 반 정도 이동하면 도착</b></i></span><span class=\"se-fs-fs19 se-ff-nanumsquare\" id=\"SE-06ff3d91-4e81-440c-b0c3-dee614452315\" style=\"color:#000000;\">할 수 있고, </span><span class=\"se-fs-fs24 se-ff-nanumsquare\" id=\"SE-9988d32d-4898-479f-a8da-899a995d4d70\" style=\"color:#000000;\"><i><b>샤코탄 반도</b></i></span><span class=\"se-fs-fs19 se-ff-nanumsquare\" id=\"SE-008707e5-dd24-469b-bac0-4d3056ee4725\" style=\"color:#000000;\"><i><b>는 홋카이도 남서부의 대표적인 해안 절경 지역</b></i></span><span class=\"se-fs-fs19 se-ff-nanumsquare\" id=\"SE-b33d8757-58ab-4c63-86dc-c7fae18c94da\" style=\"color:#000000;\">입니다.</span></p><!-- } SE-TEXT --><!-- SE-TEXT { --><p class=\"se-text-paragraph se-text-paragraph-align-justify\" id=\"SE-06d6d81b-17e4-4194-8231-c35eb7b9a382\" style=\"line-height:1.9;\"><span class=\"se-fs-fs19 se-ff-nanumsquare\" id=\"SE-9e7d4497-360f-49b1-9bba-cf8fa5e7962a\" style=\"color:#000000;\"> </span></p><!-- } SE-TEXT --><!-- SE-TEXT { --><p class=\"se-text-paragraph se-text-paragraph-align-justify se-text-paragraph-drop-cap\" id=\"SE-c1825ee8-0e84-4c80-adf7-5c4fb29889ba\" style=\"line-height:1.9;\"><span class=\"se-fs-fs19 se-ff-nanumsquare\" id=\"SE-4e609563-c793-4af3-9d8a-221feb959b58\" style=\"color:#000000;\"><span class=\"se-drop-cap\">홋</span>카이도 남서부 오타루를 지나 달리다 보면 만날 수 있는 </span><span class=\"se-fs-fs19 se-ff-nanumsquare\" id=\"SE-4403d55e-4754-4697-9d98-4f69fa13b3ec\" style=\"color:#000000;\"><i><b>샤코탄 반도는, '일본 해안절경 100선'에 선정될 만큼 압도적인 자연미를 자랑하는 곳</b></i></span><span class=\"se-fs-fs19 se-ff-nanumsquare\" id=\"SE-ba25744b-3925-47db-a7bb-eacb5b04be1a\" style=\"color:#000000;\">입니다. 그중에서도 </span><span class=\"se-fs-fs24 se-ff-nanumsquare\" id=\"SE-a45decd8-53b4-44ab-aca2-c9a69c8b53ae\" style=\"color:#000000;\"><i><b>시마무이 해안과 카무이미사키(카무이 곶)</b></i></span><span class=\"se-fs-fs19 se-ff-nanumsquare\" id=\"SE-c1ecff52-4a42-422f-a974-b8a64834e0c4\" style=\"color:#000000;\"><i><b>는 맑고 푸른 바다, 흔히 ‘샤코탄 블루’라 불리는 투명한 수평선이 특징이에요.</b></i></span></p><!-- } SE-TEXT --><!-- SE-TEXT { --><p class=\"se-text-paragraph se-text-paragraph-align-justify\" id=\"SE-63afb69d-151a-4a37-9752-5d645608c02b\" style=\"line-height:1.9;\"><span class=\"se-fs-fs19 se-ff-nanumsquare\" id=\"SE-854125ed-9fbb-4513-9c59-fed3c3800222\" style=\"color:#000000;\"> </span></p><!-- } SE-TEXT -->\n</div>\n</div>\n</div>\n\n</div> <div class=\"se-component se-image se-l-default\" id=\"SE-e2e52b4f-a61b-4dc9-9de0-fab8f1f953aa\">\n<div class=\"se-component-content se-component-content-fit\">\n<div class=\"se-section se-section-image se-l-default se-section-align-justify\">\n<div class=\"se-module se-module-image\" style=\"\">\n<a class=\"se-module-image-link __se_image_link __se_link\" data-linkdata='{\"id\" : \"SE-e2e52b4f-a61b-4dc9-9de0-fab8f1f953aa\", \"src\" : \"https://mblogthumb-phinf.pstatic.net/MjAyNTA1MjNfMjQ3/MDAxNzQ3OTk0NTIxMTQw.oQKCeSQY7w3gu72q-jdfgF4IBhSqkMWbn2yKbXCDTokg.tOkG5LekzeLjCSChVib7Y0-LQHuOjRj3Ovx-n-YFRzsg.PNG/006.png\", \"originalWidth\" : \"1080\", \"originalHeight\" : \"1080\", \"linkUse\" : \"false\", \"link\" : \"\"}' data-linktype=\"img\" href=\"#\" onclick=\"return false;\" style=\"\">\n<img alt=\"\" class=\"se-image-resource\" src=\"https://mblogthumb-phinf.pstatic.net/MjAyNTA1MjNfMjQ3/MDAxNzQ3OTk0NTIxMTQw.oQKCeSQY7w3gu72q-jdfgF4IBhSqkMWbn2yKbXCDTokg.tOkG5LekzeLjCSChVib7Y0-LQHuOjRj3Ovx-n-YFRzsg.PNG/006.png?type=w966\"/>\n</a>\n</div>\n</div>\n</div>\n\n</div>\n<div class=\"se-component se-text se-l-default\" id=\"SE-6370468b-7740-4ef8-891d-7070ceceed8f\">\n<div class=\"se-component-content\">\n<div class=\"se-section se-section-text se-l-default\">\n<div class=\"se-module se-module-text\">\n<!-- SE-TEXT { --><p class=\"se-text-paragraph se-text-paragraph-align-justify\" id=\"SE-a76a2b81-be4c-429e-83c3-e258989a06fa\" style=\"line-height:1.9;\"><span class=\"se-fs-fs19 se-ff-nanumsquare\" id=\"SE-b3cb1666-f9ad-420b-be9f-4d80a1714b28\" style=\"color:#000000;\"> </span></p><!-- } SE-TEXT --><!-- SE-TEXT { --><p class=\"se-text-paragraph se-text-paragraph-align-justify\" id=\"SE-3a637b2a-6fbf-439c-b397-92b9c3c88225\" style=\"line-height:1.9;\"><span class=\"se-fs-fs19 se-ff-nanumsquare\" id=\"SE-eb65e722-b775-44ba-9343-d686a488c9b3\" style=\"color:#000000;\">작은 터널을 지나 마주하게 되는 거대한 절벽과 암석, 그리고 그 아래로 펼쳐지는 바다의 색감은 실제로 보면 숨이 멎을 만큼 아름답습니다. </span><span class=\"se-fs-fs19 se-ff-nanumsquare\" id=\"SE-a1bf5cd0-b052-4c91-ba52-4cc550c35ff9\" style=\"color:#000000;\"><b>특히 카무이미사키 전망대에서 바라보는 촛대 바위 형태의 ‘카무이 바위’는 셔터를 멈출 수 없게 만드는 풍경입니다. </b></span><span class=\"se-fs-fs19 se-ff-nanumsquare\" id=\"SE-630f9fc0-76f2-48b6-812b-427635de13c1\" style=\"color:#000000;\">여름 햇살 아래에서 부는 시원한 바람과 함께라면, 이곳은 단연 다른 곳 저리 가라 할 정도로 멋진 여름 감성 스팟입니다.</span></p><!-- } SE-TEXT --><!-- SE-TEXT { --><p class=\"se-text-paragraph se-text-paragraph-align-justify\" id=\"SE-16890690-1a06-4273-a528-30f658ba4a65\" style=\"line-height:1.9;\"><span class=\"se-fs-fs19 se-ff-nanumsquare\" id=\"SE-bb4fe727-1708-4535-8a29-7c566f61cd61\" style=\"color:#000000;\"> </span></p><!-- } SE-TEXT -->\n</div>\n</div>\n</div>\n\n</div> <div class=\"se-component se-quotation se-l-quotation_underline\" id=\"SE-cf22119e-4014-43a1-b5ee-73aef6f8d2c7\">\n<div class=\"se-component-content\">\n<div class=\"se-section se-section-quotation se-l-quotation_underline\">\n<blockquote class=\"se-quotation-container\">\n<div class=\"se-module se-module-text se-quote\"><!-- SE-TEXT { --><p class=\"se-text-paragraph se-text-paragraph-align-\" id=\"SE-5ee86f5d-04d8-4b68-8c5c-6cfcf2d3b1c9\" style=\"\"><span class=\"se-fs-fs24 se-ff-\" id=\"SE-e5786ce2-f66e-4161-a8be-47e0e063a776\" style=\"color:#000000;\"><b>여름 홋카이도, 사진 찍을 때 꼭 기억할 점은?</b></span></p><!-- } SE-TEXT --></div>\n</blockquote>\n</div>\n</div>\n</div>\n<div class=\"se-component se-image se-l-default\" id=\"SE-fd22a15c-4247-4967-a473-4dee36ff3723\">\n<div class=\"se-component-content se-component-content-fit\">\n<div class=\"se-section se-section-image se-l-default se-section-align-justify\">\n<div class=\"se-module se-module-image\" style=\"\">\n<a class=\"se-module-image-link __se_image_link __se_link\" data-linkdata='{\"id\" : \"SE-fd22a15c-4247-4967-a473-4dee36ff3723\", \"src\" : \"https://mblogthumb-phinf.pstatic.net/MjAyNTA1MjNfMTUy/MDAxNzQ3OTk0NTIzNDU3.9aBkp46Mfk8eOog1hTAHPMR2roLtFSSmA-ZUO67zehwg.-xauF1-Eae1xzTPVkkZE5HUX70NEEErqhXe_8XWXeVEg.PNG/007.png\", \"originalWidth\" : \"1080\", \"originalHeight\" : \"1080\", \"linkUse\" : \"false\", \"link\" : \"\"}' data-linktype=\"img\" href=\"#\" onclick=\"return false;\" style=\"\">\n<img alt=\"\" class=\"se-image-resource\" src=\"https://mblogthumb-phinf.pstatic.net/MjAyNTA1MjNfMTUy/MDAxNzQ3OTk0NTIzNDU3.9aBkp46Mfk8eOog1hTAHPMR2roLtFSSmA-ZUO67zehwg.-xauF1-Eae1xzTPVkkZE5HUX70NEEErqhXe_8XWXeVEg.PNG/007.png?type=w966\"/>\n</a>\n</div>\n</div>\n</div>\n\n</div>\n<div class=\"se-component se-text se-l-default\" id=\"SE-44b2406f-47fa-43cf-88b7-ce83be50eccc\">\n<div class=\"se-component-content\">\n<div class=\"se-section se-section-text se-l-default\">\n<div class=\"se-module se-module-text\">\n<!-- SE-TEXT { --><p class=\"se-text-paragraph se-text-paragraph-align-justify\" id=\"SE-844bec07-01c9-4a9f-bcf2-23be391e260e\" style=\"line-height:1.9;\"><span class=\"se-fs-fs19 se-ff-nanumsquare\" id=\"SE-3d205a0f-e45b-4016-935d-8c863d9f7f2c\" style=\"color:#000000;\"> </span></p><!-- } SE-TEXT --><!-- SE-TEXT { --><p class=\"se-text-paragraph se-text-paragraph-align-justify se-text-paragraph-drop-cap\" id=\"SE-464bdeeb-ddf5-44cf-bca0-25d9411bfb43\" style=\"line-height:1.9;\"><span class=\"se-fs-fs19 se-ff-nanumsquare\" id=\"SE-a7046066-dd70-43d4-86b4-b935f87d8e8a\" style=\"color:#000000;\"><b><span class=\"se-drop-cap\">여</span>름 홋카이도는 맑고 선선한 날씨 덕분에 사진 찍기 좋은 계절인데요. 꼭 시간대를 체크해 주시면 좋습니다.</b></span><span class=\"se-fs-fs19 se-ff-nanumsquare\" id=\"SE-8844b7db-a3e7-44cc-a0d8-aa41b8932397\" style=\"color:#000000;\"><i><b> 특히 아침 시간대는 햇살이 부드럽고 사람도 적어, 여유롭게 촬영할 수 있답니다.</b></i></span><span class=\"se-fs-fs19 se-ff-nanumsquare\" id=\"SE-89072556-ddb1-4316-a2b7-4dc74adc180a\" style=\"color:#000000;\"><i><b>​</b></i></span></p><!-- } SE-TEXT --><!-- SE-TEXT { --><p class=\"se-text-paragraph se-text-paragraph-align-justify\" id=\"SE-a8cd9335-da4b-438e-a95e-798219590487\" style=\"line-height:1.9;\"><span class=\"se-fs-fs19 se-ff-nanumsquare\" id=\"SE-f8110e08-e2e6-42ef-a9bc-30f25a2bad71\" style=\"color:#000000;\"> </span></p><!-- } SE-TEXT --><!-- SE-TEXT { --><p class=\"se-text-paragraph se-text-paragraph-align-justify\" id=\"SE-8c68da48-cf07-498d-b302-127ecd177dc3\" style=\"line-height:1.9;\"><span class=\"se-fs-fs19 se-ff-nanumsquare\" id=\"SE-0be78f83-ec87-47e0-af2c-40659c65ef38\" style=\"color:#000000;\"><u>청의 호수(아오이이케)는 아침 7시 전후</u></span><span class=\"se-fs-fs19 se-ff-nanumsquare\" id=\"SE-9084faa0-d8a1-4286-b2dd-966d195a03c3\" style=\"color:#000000;\">에 바람이 적고 수면이 잔잔해, 나무와 하늘이 고스란히 비치는 반영 사진을 담기 좋은데요. </span><span class=\"se-fs-fs19 se-ff-nanumsquare\" id=\"SE-a34846c4-a470-44d4-aff1-23a65442aa2d\" style=\"color:#000000;\"><u>맑은 날에는 푸른빛이 더욱 선명해져 인생 샷을 남기기 딱 좋은 타이밍을 가질 수 있습니다.</u></span></p><!-- } SE-TEXT --><!-- SE-TEXT { --><p class=\"se-text-paragraph se-text-paragraph-align-justify\" id=\"SE-e16c4d0e-d5ae-40bc-9f8f-088e440f94d9\" style=\"line-height:1.9;\"><span class=\"se-fs-fs19 se-ff-nanumsquare\" id=\"SE-7ff428c7-75f3-482e-a26b-8d0b10339c53\" style=\"color:#000000;\"> </span></p><!-- } SE-TEXT --><!-- SE-TEXT { --><p class=\"se-text-paragraph se-text-paragraph-align-justify\" id=\"SE-a4b24261-146c-41f9-a9ef-ded0b0f9aba2\" style=\"line-height:1.9;\"><span class=\"se-fs-fs19 se-ff-nanumsquare\" id=\"SE-89afd08c-6648-4e38-b6b7-c43687d0ecae\" style=\"color:#000000;\"><u>팜 토미타 역시 여름철 인기가 많은 명소라 아침 일찍</u></span><span class=\"se-fs-fs19 se-ff-nanumsquare\" id=\"SE-62c3c3b4-3324-425f-8382-e95691fad715\" style=\"color:#000000;\"> 방문하시면 좋은데요. 오전 시간대가 비교적 한산하고 햇살도 부드러워, 보랏빛 라벤더가 은은하게 담길거에요.</span></p><!-- } SE-TEXT --><!-- SE-TEXT { --><p class=\"se-text-paragraph se-text-paragraph-align-justify\" id=\"SE-944a587c-0e1a-4b4f-b29a-13f4a603da36\" style=\"line-height:1.9;\"><span class=\"se-fs-fs19 se-ff-nanumsquare\" id=\"SE-41dd5013-5e7f-4163-8011-1653eea5fb52\" style=\"color:#000000;\"> </span></p><!-- } SE-TEXT -->\n</div>\n</div>\n</div>\n\n</div> <div class=\"se-component se-image se-l-default\" id=\"SE-b5824773-1dbc-48da-9d9e-748d3953031e\">\n<div class=\"se-component-content se-component-content-fit\">\n<div class=\"se-section se-section-image se-l-default se-section-align-justify\">\n<div class=\"se-module se-module-image\" style=\"\">\n<a class=\"se-module-image-link __se_image_link __se_link\" data-linkdata='{\"id\" : \"SE-b5824773-1dbc-48da-9d9e-748d3953031e\", \"src\" : \"https://mblogthumb-phinf.pstatic.net/MjAyNTA1MjNfOTkg/MDAxNzQ3OTk0NTI2MjEy.m-WRtW5gRCX1gtbAWr9xE5r9imaUEoHHiZOKyt1Pdz0g.y161yp5lWnZXbeyjjRPNwnl-YRWlACBgKILmlr0AUVcg.PNG/008.png\", \"originalWidth\" : \"1080\", \"originalHeight\" : \"1080\", \"linkUse\" : \"false\", \"link\" : \"\"}' data-linktype=\"img\" href=\"#\" onclick=\"return false;\" style=\"\">\n<img alt=\"\" class=\"se-image-resource\" src=\"https://mblogthumb-phinf.pstatic.net/MjAyNTA1MjNfOTkg/MDAxNzQ3OTk0NTI2MjEy.m-WRtW5gRCX1gtbAWr9xE5r9imaUEoHHiZOKyt1Pdz0g.y161yp5lWnZXbeyjjRPNwnl-YRWlACBgKILmlr0AUVcg.PNG/008.png?type=w966\"/>\n</a>\n</div>\n</div>\n</div>\n\n</div>\n<div class=\"se-component se-text se-l-default\" id=\"SE-bdc5550e-2639-440d-b4b0-776cdb7b8a3e\">\n<div class=\"se-component-content\">\n<div class=\"se-section se-section-text se-l-default\">\n<div class=\"se-module se-module-text\">\n<!-- SE-TEXT { --><p class=\"se-text-paragraph se-text-paragraph-align-justify\" id=\"SE-a6f45c72-18bd-44db-b099-50ba906156dc\" style=\"line-height:1.9;\"><span class=\"se-fs-fs19 se-ff-nanumsquare\" id=\"SE-5bc5c45c-a713-4669-b492-ed48e68580c9\" style=\"color:#000000;\"> </span></p><!-- } SE-TEXT --><!-- SE-TEXT { --><p class=\"se-text-paragraph se-text-paragraph-align-justify se-text-paragraph-drop-cap\" id=\"SE-e1bec20c-4e9a-499e-a11d-94ed83248c73\" style=\"line-height:1.9;\"><span class=\"se-fs-fs19 se-ff-nanumsquare\" id=\"SE-4b9bd56a-1dde-4635-b174-269221fe0180\" style=\"color:#000000;\"><i><b><span class=\"se-drop-cap\">여</span>름의 자연을 제대로 담고 싶다면 광각 렌즈로 넓은 경관을, 삼각대로 안정감 있는 구도를 잡는 것도 좋은 팁인데요. 스마트폰으로도 충분히 아름답게 찍을 수 있지만, 파노라마 기능을 활용하면 라벤더 밭이나 해안 풍경도 더 넓고 풍부하게 담을 수 있어요.</b></i></span></p><!-- } SE-TEXT --><!-- SE-TEXT { --><p class=\"se-text-paragraph se-text-paragraph-align-justify\" id=\"SE-defb3307-c7fb-4a7c-926f-2074f848f223\" style=\"line-height:1.9;\"><span class=\"se-fs-fs19 se-ff-nanumsquare\" id=\"SE-de7dcf89-a041-45bb-8a29-0cca576d1e87\" style=\"color:#000000;\"> </span></p><!-- } SE-TEXT -->\n</div>\n</div>\n</div>\n\n</div> <div class=\"se-component se-quotation se-l-quotation_underline\" id=\"SE-2cfc28a0-79c7-4ba8-8a1f-9614e65c1f61\">\n<div class=\"se-component-content\">\n<div class=\"se-section se-section-quotation se-l-quotation_underline\">\n<blockquote class=\"se-quotation-container\">\n<div class=\"se-module se-module-text se-quote\"><!-- SE-TEXT { --><p class=\"se-text-paragraph se-text-paragraph-align-\" id=\"SE-a4fa87e0-9d6d-4476-8431-a0ad85f029e3\" style=\"\"><span class=\"se-fs-fs24 se-ff-\" id=\"SE-3e5c69f1-54ad-4e00-8fe9-23b3e03e9969\" style=\"color:#000000;\"><b>감성보다는 ‘완성도’가 중요한 여행 포토북,</b></span></p><!-- } SE-TEXT --><!-- SE-TEXT { --><p class=\"se-text-paragraph se-text-paragraph-align-\" id=\"SE-a093b945-0bcd-4197-957f-2999ea6bc019\" style=\"\"><span class=\"se-fs-fs24 se-ff-\" id=\"SE-e99ae11b-6c8b-4b96-8649-74980a807bc4\" style=\"color:#000000;\"><b>점보포토로 만드는 이유</b></span></p><!-- } SE-TEXT --></div>\n</blockquote>\n</div>\n</div>\n</div>\n<div class=\"se-component se-image se-l-default\" id=\"SE-5b8296cc-52f2-43dd-969b-8573439985a7\">\n<div class=\"se-component-content se-component-content-fit\">\n<div class=\"se-section se-section-image se-l-default se-section-align-justify\">\n<div class=\"se-module se-module-image\" style=\"\">\n<a class=\"se-module-image-link __se_image_link __se_link\" data-linkdata='{\"id\" : \"SE-5b8296cc-52f2-43dd-969b-8573439985a7\", \"src\" : \"https://mblogthumb-phinf.pstatic.net/MjAyNTA1MjNfNDcg/MDAxNzQ3OTk0NTI4NzYx.HWDVbdOcnuMfR9vipoBXgXr6zU--FZb4F8fTqleZC_Ig.WUQor7-a6edVfJJb8IlvHjBd8RIxAegr5T8dQtCsYv4g.PNG/009.png\", \"originalWidth\" : \"1080\", \"originalHeight\" : \"1080\", \"linkUse\" : \"false\", \"link\" : \"\"}' data-linktype=\"img\" href=\"#\" onclick=\"return false;\" style=\"\">\n<img alt=\"\" class=\"se-image-resource\" src=\"https://mblogthumb-phinf.pstatic.net/MjAyNTA1MjNfNDcg/MDAxNzQ3OTk0NTI4NzYx.HWDVbdOcnuMfR9vipoBXgXr6zU--FZb4F8fTqleZC_Ig.WUQor7-a6edVfJJb8IlvHjBd8RIxAegr5T8dQtCsYv4g.PNG/009.png?type=w966\"/>\n</a>\n</div>\n</div>\n</div>\n\n</div>\n<div class=\"se-component se-text se-l-default\" id=\"SE-d1a85156-2749-4475-a599-19d2aa8ee7af\">\n<div class=\"se-component-content\">\n<div class=\"se-section se-section-text se-l-default\">\n<div class=\"se-module se-module-text\">\n<!-- SE-TEXT { --><p class=\"se-text-paragraph se-text-paragraph-align-justify\" id=\"SE-9c23c82b-cafa-4758-98ee-2dfdaa7570e4\" style=\"line-height:1.9;\"><span class=\"se-fs-fs19 se-ff-nanumsquare\" id=\"SE-626eea84-e9b4-45ab-9e8e-687016eb8402\" style=\"color:#000000;\"> </span></p><!-- } SE-TEXT --><!-- SE-TEXT { --><p class=\"se-text-paragraph se-text-paragraph-align-justify se-text-paragraph-drop-cap\" id=\"SE-5ec139ad-4678-4c3b-86f4-9a5075ddc930\" style=\"line-height:1.9;\"><span class=\"se-fs-fs19 se-ff-nanumsquare\" id=\"SE-bdf65b30-7834-4ebd-a825-df44bddbe9d3\" style=\"color:#000000;\"><span class=\"se-drop-cap\">사</span>진을 많이 찍는 여행일수록, 막상 정리할 때는 “괜히 찍었나...” 싶을 정도로 귀찮아집니다. 하지만 한 번쯤은, 진짜 제대로 남기고 싶은 여행이 있죠. </span><span class=\"se-fs-fs19 se-ff-nanumsquare\" id=\"SE-beceeb28-bc1f-4baa-9c0e-d57a52b548ba\" style=\"color:#000000;\"><i>여름 홋카이도처럼 풍경 위주로 사진이 많은 여행이라면, 포토북도 감성보다는 완성도와 품질이 중요하겠죠.</i></span></p><!-- } SE-TEXT --><!-- SE-TEXT { --><p class=\"se-text-paragraph se-text-paragraph-align-justify\" id=\"SE-26cfaf2c-a219-4bcd-a9af-4dc5a400c3c4\" style=\"line-height:1.9;\"><span class=\"se-fs-fs19 se-ff-nanumsquare\" id=\"SE-eefe88c5-454d-4afc-96ae-1b612fc730bf\" style=\"color:#000000;\"> </span></p><!-- } SE-TEXT -->\n</div>\n</div>\n</div>\n\n</div> <div class=\"se-component se-quotation se-l-quotation_line\" id=\"SE-e9e50cc6-9084-4cb2-91b0-dc427e76357e\">\n<div class=\"se-component-content\">\n<div class=\"se-section se-section-quotation se-l-quotation_line\">\n<blockquote class=\"se-quotation-container\">\n<div class=\"se-module se-module-text se-quote\"><!-- SE-TEXT { --><p class=\"se-text-paragraph se-text-paragraph-align-\" id=\"SE-ff033bb5-d74d-4a35-be55-d1b034b65e60\" style=\"\"><span class=\"se-fs-fs24 se-ff-\" id=\"SE-a72f29f4-de43-460c-a0ad-60312e37639a\" style=\"color:#000000;\"><b>인디고 인쇄 + 후지 정품지, 포토북의 기본이 다릅니다.</b></span></p><!-- } SE-TEXT --></div>\n</blockquote>\n</div>\n</div>\n</div>\n<div class=\"se-component se-image se-l-default\" id=\"SE-290d18ed-98db-4216-8656-c1314c5b152d\">\n<div class=\"se-component-content se-component-content-fit\">\n<div class=\"se-section se-section-image se-l-default se-section-align-justify\">\n<div class=\"se-module se-module-image\" style=\"\">\n<a class=\"se-module-image-link __se_image_link __se_link\" data-linkdata='{\"id\" : \"SE-290d18ed-98db-4216-8656-c1314c5b152d\", \"src\" : \"https://mblogthumb-phinf.pstatic.net/MjAyNTA1MjNfMjg4/MDAxNzQ3OTk0NTMxMjA1.IQ-EJpw8klHVR67n5mqr1wiPDHKVkebTHyqkTFS8BpEg.RljPfc4CrDmiiur_KU1fVOkM0FPMyQ3ioU2F7Pzew1kg.PNG/010.png\", \"originalWidth\" : \"1080\", \"originalHeight\" : \"1080\", \"linkUse\" : \"false\", \"link\" : \"\"}' data-linktype=\"img\" href=\"#\" onclick=\"return false;\" style=\"\">\n<img alt=\"\" class=\"se-image-resource\" src=\"https://mblogthumb-phinf.pstatic.net/MjAyNTA1MjNfMjg4/MDAxNzQ3OTk0NTMxMjA1.IQ-EJpw8klHVR67n5mqr1wiPDHKVkebTHyqkTFS8BpEg.RljPfc4CrDmiiur_KU1fVOkM0FPMyQ3ioU2F7Pzew1kg.PNG/010.png?type=w966\"/>\n</a>\n</div>\n</div>\n</div>\n\n</div>\n<div class=\"se-component se-text se-l-default\" id=\"SE-927c9549-8b43-4d59-8a1e-1040c9dae28a\">\n<div class=\"se-component-content\">\n<div class=\"se-section se-section-text se-l-default\">\n<div class=\"se-module se-module-text\">\n<!-- SE-TEXT { --><p class=\"se-text-paragraph se-text-paragraph-align-justify se-text-paragraph-drop-cap\" id=\"SE-f4a8c4d7-1230-4add-9deb-1f02e683ff2e\" style=\"line-height:1.9;\"><span class=\"se-fs-fs19 se-ff-nanumsquare\" id=\"SE-98656583-4c5c-48e9-8bd2-779162579afc\" style=\"color:#000000;\"><span class=\"se-drop-cap\">점</span>보포토 포토북은 인쇄 방식부터 다릅니다. 일반 출력이 아닌 </span><span class=\"se-fs-fs19 se-ff-nanumsquare\" id=\"SE-d17eb84d-14d9-4966-bd2a-0945a524de7d\" style=\"color:#00cdff;\"><b>인디고 디지털 인쇄 방식을 사용해, 섬세한 색감과 사진의 질감을 제대로 표현해 줍니다.</b></span><span class=\"se-fs-fs19 se-ff-nanumsquare\" id=\"SE-cf2aca82-e3f5-4e0e-ac24-715d9b36e071\" style=\"color:#000000;\"> </span></p><!-- } SE-TEXT --><!-- SE-TEXT { --><p class=\"se-text-paragraph se-text-paragraph-align-justify\" id=\"SE-a42b6f01-4c9f-490c-a6d1-d7cfc30e930e\" style=\"line-height:1.9;\"><span class=\"se-fs-fs19 se-ff-nanumsquare\" id=\"SE-7fb674f4-7c51-4a54-921d-23dc99f48df9\" style=\"color:#000000;\">​</span></p><!-- } SE-TEXT --><!-- SE-TEXT { --><p class=\"se-text-paragraph se-text-paragraph-align-justify\" id=\"SE-8f376ba2-397f-4bba-864c-d232aa28e1b7\" style=\"line-height:1.9;\"><span class=\"se-fs-fs19 se-ff-nanumsquare\" id=\"SE-4c1e4f46-6833-4076-86de-fcc303238472\" style=\"color:#00cdff;\"><b>여기에 후지필름 QPDP 정품 인증지를 사용해 색 번짐 없이 또렷하고 깊이감 있는 사진 결과물을 얻을 수 있고, 장시간 보관해도 색이 쉽게 바래지지 않습니다.</b></span><span class=\"se-fs-fs19 se-ff-nanumsquare\" id=\"SE-b956fa10-72b1-4e87-b782-5c057e1b8def\" style=\"color:#000000;\"> 여행지를 배경으로 한 풍경 사진, 특히 라벤더 밭이나 바다처럼 색감이 중요한 장면에서는 이 차이가 훨씬 크게 느껴질 거예요.</span></p><!-- } SE-TEXT --><!-- SE-TEXT { --><p class=\"se-text-paragraph se-text-paragraph-align-justify\" id=\"SE-bfcd9608-e97b-47ef-8e80-92ab4181052c\" style=\"line-height:1.9;\"><span class=\"se-fs-fs19 se-ff-nanumsquare\" id=\"SE-fe72fc5b-0a36-415c-a3ae-c5b4752db8e0\" style=\"color:#000000;\"> </span></p><!-- } SE-TEXT -->\n</div>\n</div>\n</div>\n\n</div> <div class=\"se-component se-quotation se-l-quotation_line\" id=\"SE-3f82cbb4-0e0d-4dba-8b20-8a7caaf90309\">\n<div class=\"se-component-content\">\n<div class=\"se-section se-section-quotation se-l-quotation_line\">\n<blockquote class=\"se-quotation-container\">\n<div class=\"se-module se-module-text se-quote\"><!-- SE-TEXT { --><p class=\"se-text-paragraph se-text-paragraph-align-\" id=\"SE-716dbc2e-a501-4fc6-85d2-217d317d2595\" style=\"\"><span class=\"se-fs-fs24 se-ff-\" id=\"SE-7007baad-6a54-4108-8411-e4d70bdb4648\" style=\"color:#000000;\"><b>여행에 맞춘 디자인, 고민 없이 감성 있는 구성</b></span></p><!-- } SE-TEXT --></div>\n</blockquote>\n</div>\n</div>\n</div>\n<div class=\"se-component se-image se-l-default\" id=\"SE-8dae714b-7dcc-44e3-8a7e-6e666abff7a0\">\n<div class=\"se-component-content se-component-content-fit\">\n<div class=\"se-section se-section-image se-l-default se-section-align-justify\">\n<div class=\"se-module se-module-image\" style=\"\">\n<a class=\"se-module-image-link __se_image_link __se_link\" data-linkdata='{\"id\" : \"SE-8dae714b-7dcc-44e3-8a7e-6e666abff7a0\", \"src\" : \"https://mblogthumb-phinf.pstatic.net/MjAyNTA1MjNfMTQg/MDAxNzQ3OTk0NTMzODg1.MREzKk5qreRL_sAGVZQOxhsSNPUxwSIxa74EJeSTxWog.TLbmOiRQI8_M6lRyMYS71WOr6Fzh0C4ekVOc2cSCd6gg.PNG/011.png\", \"originalWidth\" : \"1080\", \"originalHeight\" : \"1080\", \"linkUse\" : \"false\", \"link\" : \"\"}' data-linktype=\"img\" href=\"#\" onclick=\"return false;\" style=\"\">\n<img alt=\"\" class=\"se-image-resource\" src=\"https://mblogthumb-phinf.pstatic.net/MjAyNTA1MjNfMTQg/MDAxNzQ3OTk0NTMzODg1.MREzKk5qreRL_sAGVZQOxhsSNPUxwSIxa74EJeSTxWog.TLbmOiRQI8_M6lRyMYS71WOr6Fzh0C4ekVOc2cSCd6gg.PNG/011.png?type=w966\"/>\n</a>\n</div>\n</div>\n</div>\n\n</div>\n<div class=\"se-component se-text se-l-default\" id=\"SE-28a21e34-d837-43e4-974b-0e4ce0f53a0a\">\n<div class=\"se-component-content\">\n<div class=\"se-section se-section-text se-l-default\">\n<div class=\"se-module se-module-text\">\n<!-- SE-TEXT { --><p class=\"se-text-paragraph se-text-paragraph-align-justify\" id=\"SE-57a4604d-4a7f-4575-9181-1f5f29eecfa7\" style=\"line-height:1.9;\"><span class=\"se-fs-fs19 se-ff-nanumsquare\" id=\"SE-6366430f-63c8-4b0c-90a9-c590f702eca4\" style=\"color:#000000;\">​</span></p><!-- } SE-TEXT --><!-- SE-TEXT { --><p class=\"se-text-paragraph se-text-paragraph-align-justify se-text-paragraph-drop-cap\" id=\"SE-17fc806a-ee78-4909-a41c-1fec2c104864\" style=\"line-height:1.9;\"><span class=\"se-fs-fs19 se-ff-nanumsquare\" id=\"SE-4ffea50a-8cec-4640-9d67-067626b10063\" style=\"color:#00cdff;\"><b><span class=\"se-drop-cap\">점</span>보포토는 여행 사진 정리에 특화된 지역별 테마 템플릿이 잘 준비되어 있어, 따로 디자인을 고민하지 않아도 감성적인 구성이 가능합니다. </b></span></p><!-- } SE-TEXT --><!-- SE-TEXT { --><p class=\"se-text-paragraph se-text-paragraph-align-justify\" id=\"SE-624e93e7-a174-4561-9fbb-6334def0a543\" style=\"line-height:1.9;\"><span class=\"se-fs-fs19 se-ff-nanumsquare\" id=\"SE-769718d7-ed63-4d5b-ab42-94c1d82569e1\" style=\"color:#000000;\">​</span></p><!-- } SE-TEXT --><!-- SE-TEXT { --><p class=\"se-text-paragraph se-text-paragraph-align-justify\" id=\"SE-6ddb8165-1996-4062-8630-da3fc6cc49b1\" style=\"line-height:1.9;\"><span class=\"se-fs-fs19 se-ff-nanumsquare\" id=\"SE-816d7a57-94cb-4aec-ac39-0b54dd933d0d\" style=\"color:#000000;\">홋카이도처럼 여백과 빛이 중요한 사진에는 미니멀하고 깔끔한 레이아웃이 자연스럽게 어울리고, 여정 중심으로 구성하고 싶을 때에도 흐름이 매끄럽게 이어지도록 설계되어 있어 편하게 작업하실 수 있습니다.</span></p><!-- } SE-TEXT --><!-- SE-TEXT { --><p class=\"se-text-paragraph se-text-paragraph-align-justify\" id=\"SE-8c4b9ed1-9969-40b8-86bd-46fadc46fbee\" style=\"line-height:1.9;\"><span class=\"se-fs-fs19 se-ff-nanumsquare\" id=\"SE-403dbc50-33d7-4b62-a653-6adc92b84c81\" style=\"color:#000000;\"> </span></p><!-- } SE-TEXT -->\n</div>\n</div>\n</div>\n\n</div> <div class=\"se-component se-quotation se-l-quotation_line\" id=\"SE-1a2d22ab-041b-4989-958a-15967c106bcd\">\n<div class=\"se-component-content\">\n<div class=\"se-section se-section-quotation se-l-quotation_line\">\n<blockquote class=\"se-quotation-container\">\n<div class=\"se-module se-module-text se-quote\"><!-- SE-TEXT { --><p class=\"se-text-paragraph se-text-paragraph-align-\" id=\"SE-6f603ef0-fe6d-49b9-b5f5-c75a72d4b953\" style=\"\"><span class=\"se-fs-fs24 se-ff-\" id=\"SE-ccad5ad8-29e9-43ab-bb49-c47b2daac039\" style=\"color:#000000;\"><b>고급 커버 옵션과 코팅 마감까지, 오래 두고 보기 좋은 포토북</b></span></p><!-- } SE-TEXT --></div>\n</blockquote>\n</div>\n</div>\n</div>\n<div class=\"se-component se-image se-l-default\" id=\"SE-604bff61-a230-4166-ae09-86731309e604\">\n<div class=\"se-component-content se-component-content-fit\">\n<div class=\"se-section se-section-image se-l-default se-section-align-justify\">\n<div class=\"se-module se-module-image\" style=\"\">\n<a class=\"se-module-image-link __se_image_link __se_link\" data-linkdata='{\"id\" : \"SE-604bff61-a230-4166-ae09-86731309e604\", \"src\" : \"https://mblogthumb-phinf.pstatic.net/MjAyNTA1MjNfNzQg/MDAxNzQ3OTk0NTM2MTcz.1v_J6ccN96LhvlOQvN9HM0G5t7Vd64RWWJB5_sT6OGEg.ZHHahLNwGrQhe7gO_LnrmC29LYwh2HtbyNxpCijVZTkg.PNG/012.png\", \"originalWidth\" : \"1080\", \"originalHeight\" : \"1080\", \"linkUse\" : \"false\", \"link\" : \"\"}' data-linktype=\"img\" href=\"#\" onclick=\"return false;\" style=\"\">\n<img alt=\"\" class=\"se-image-resource\" src=\"https://mblogthumb-phinf.pstatic.net/MjAyNTA1MjNfNzQg/MDAxNzQ3OTk0NTM2MTcz.1v_J6ccN96LhvlOQvN9HM0G5t7Vd64RWWJB5_sT6OGEg.ZHHahLNwGrQhe7gO_LnrmC29LYwh2HtbyNxpCijVZTkg.PNG/012.png?type=w966\"/>\n</a>\n</div>\n</div>\n</div>\n\n</div>\n<div class=\"se-component se-text se-l-default\" id=\"SE-ab2e2b67-a686-4b5c-b275-354617a6a6fa\">\n<div class=\"se-component-content\">\n<div class=\"se-section se-section-text se-l-default\">\n<div class=\"se-module se-module-text\">\n<!-- SE-TEXT { --><p class=\"se-text-paragraph se-text-paragraph-align-justify\" id=\"SE-17024ecb-94d1-427b-8aae-82b975f375d0\" style=\"line-height:1.9;\"><span class=\"se-fs-fs19 se-ff-nanumsquare\" id=\"SE-112c0c78-94ee-48fa-a5f0-4de5153bc7b4\" style=\"color:#000000;\">​</span></p><!-- } SE-TEXT --><!-- SE-TEXT { --><p class=\"se-text-paragraph se-text-paragraph-align-justify se-text-paragraph-drop-cap\" id=\"SE-833195be-f50b-426a-8a07-11ecc1791cd3\" style=\"line-height:1.9;\"><span class=\"se-fs-fs19 se-ff-nanumsquare\" id=\"SE-49d92ba0-9b6b-44f7-8f34-079548fa7865\" style=\"color:#000000;\"><span class=\"se-drop-cap\">기</span>억을 오래 간직하고 싶은 여행이라면 표지부터 다르게 선택하는 게 좋습니다. </span><span class=\"se-fs-fs19 se-ff-nanumsquare\" id=\"SE-ce1b6dfb-2e0d-4f1d-bef0-5d11fbe060b9\" style=\"color:#00cdff;\"><b>점보포토에서는 일반 하드커버 포토북뿐만 아니라, 레이플렛 포토북, 프라임 포토북 다양한데요. </b></span><span class=\"se-fs-fs19 se-ff-nanumsquare\" id=\"SE-09b55861-d64d-4867-9af7-69be16059cc5\" style=\"color:#000000;background-color:#b0f1ff;\"><b>특히 프라임 포토북은 고급 레더나 패브릭 커버로 더욱 고급지게 여행을 담아낼 수 있습니다. </b></span><span class=\"se-fs-fs19 se-ff-nanumsquare\" id=\"SE-3f53797f-ca57-4ca2-b8a9-d153aef7ad45\" style=\"color:#000000;\">커버 색상도 20종 이상으로 다양하게 준비되어 있어 취향에 맞게 고를 수 있습니다. </span></p><!-- } SE-TEXT --><!-- SE-TEXT { --><p class=\"se-text-paragraph se-text-paragraph-align-justify\" id=\"SE-b32bbb14-2534-4d05-9dce-39d4804a4709\" style=\"line-height:1.9;\"><span class=\"se-fs-fs19 se-ff-nanumsquare\" id=\"SE-f4632c2f-75a7-41e7-8fab-a945b55e5e48\" style=\"color:#000000;\">​</span></p><!-- } SE-TEXT --><!-- SE-TEXT { --><p class=\"se-text-paragraph se-text-paragraph-align-justify\" id=\"SE-3b1216f7-34f7-4705-8acd-d4a1af52faf4\" style=\"line-height:1.9;\"><span class=\"se-fs-fs19 se-ff-nanumsquare\" id=\"SE-13a6cac3-1d89-42e1-8e5f-f629a02a8529\" style=\"color:#00cdff;\"><b>여기에 UV 유무광코팅도 업계 유일하게 무료이니, 원하는 코팅 방식을 선택하여 마무리하면, 오염에도 강하고 색감 보존력도 높아져 오래 두고 보기 좋은 포토북이 완성된답니다.</b></span><span class=\"se-fs-fs19 se-ff-nanumsquare\" id=\"SE-e6a10a5b-952c-47e3-b944-e2261b3ab3c2\" style=\"color:#000000;\"> 특히 레이플랫 제본을 선택하면 사진이 중앙에서 끊기지 않고 180도 펼쳐지기 때문에 풍경 사진을 크게 담고 싶은 분들께 추천드려요.</span></p><!-- } SE-TEXT --><!-- SE-TEXT { --><p class=\"se-text-paragraph se-text-paragraph-align-justify\" id=\"SE-7a63da20-f991-47cd-b022-13548e6e89f6\" style=\"line-height:1.9;\"><span class=\"se-fs-fs19 se-ff-nanumsquare\" id=\"SE-b5870399-aa96-46da-b61e-a7188d9a93dd\" style=\"color:#000000;\"> </span></p><!-- } SE-TEXT -->\n</div>\n</div>\n</div>\n\n</div> <div class=\"se-component se-quotation se-l-quotation_line\" id=\"SE-c4fcc82e-0c6a-42e6-96ac-5f47dd1b3236\">\n<div class=\"se-component-content\">\n<div class=\"se-section se-section-quotation se-l-quotation_line\">\n<blockquote class=\"se-quotation-container\">\n<div class=\"se-module se-module-text se-quote\"><!-- SE-TEXT { --><p class=\"se-text-paragraph se-text-paragraph-align-\" id=\"SE-35be8f9c-67e2-48d6-b27b-5ed994d4b6be\" style=\"\"><span class=\"se-fs-fs24 se-ff-\" id=\"SE-dd1f1cb4-a0e6-488f-9ae4-c122db273d24\" style=\"color:#000000;\"><b>편집은 간편하게, 결과물은 전문가처럼</b></span></p><!-- } SE-TEXT --></div>\n</blockquote>\n</div>\n</div>\n</div>\n<div class=\"se-component se-image se-l-default\" id=\"SE-648a5765-2600-498b-a5c2-a82d869d01de\">\n<div class=\"se-component-content se-component-content-fit\">\n<div class=\"se-section se-section-image se-l-default se-section-align-justify\">\n<div class=\"se-module se-module-image\" style=\"\">\n<a class=\"se-module-image-link __se_image_link __se_link\" data-linkdata='{\"id\" : \"SE-648a5765-2600-498b-a5c2-a82d869d01de\", \"src\" : \"https://mblogthumb-phinf.pstatic.net/MjAyNTA1MjNfNDAg/MDAxNzQ3OTk0NTM4NjEy.hBHQMlOvaW3t8SHpicFUqIQuZAHOLAcZFLvdcKjkL8wg.TtixAwQpF90MB5Uc_CWuFi3yHVKCOzYnbZ0ffUfbggcg.PNG/013.png\", \"originalWidth\" : \"1080\", \"originalHeight\" : \"1080\", \"linkUse\" : \"false\", \"link\" : \"\"}' data-linktype=\"img\" href=\"#\" onclick=\"return false;\" style=\"\">\n<img alt=\"\" class=\"se-image-resource\" src=\"https://mblogthumb-phinf.pstatic.net/MjAyNTA1MjNfNDAg/MDAxNzQ3OTk0NTM4NjEy.hBHQMlOvaW3t8SHpicFUqIQuZAHOLAcZFLvdcKjkL8wg.TtixAwQpF90MB5Uc_CWuFi3yHVKCOzYnbZ0ffUfbggcg.PNG/013.png?type=w966\"/>\n</a>\n</div>\n</div>\n</div>\n\n</div>\n<div class=\"se-component se-text se-l-default\" id=\"SE-1ef234d9-f334-4e33-91e3-566fd510290f\">\n<div class=\"se-component-content\">\n<div class=\"se-section se-section-text se-l-default\">\n<div class=\"se-module se-module-text\">\n<!-- SE-TEXT { --><p class=\"se-text-paragraph se-text-paragraph-align-justify\" id=\"SE-6e627b69-8666-477d-b93c-dd67634b992b\" style=\"line-height:1.9;\"><span class=\"se-fs-fs19 se-ff-nanumsquare\" id=\"SE-4f2e8efb-d345-49a0-ab48-d8dad139dbc9\" style=\"color:#000000;\">​</span></p><!-- } SE-TEXT --><!-- SE-TEXT { --><p class=\"se-text-paragraph se-text-paragraph-align-justify se-text-paragraph-drop-cap\" id=\"SE-8c8c82ce-693e-4cc8-84ad-04df8684031c\" style=\"line-height:1.9;\"><span class=\"se-fs-fs19 se-ff-nanumsquare\" id=\"SE-06916c04-fd47-4d36-81e4-5caa03bccf90\" style=\"color:#00cdff;\"><b><span class=\"se-drop-cap\">직</span>관적인 편집 프로그램 덕분에 처음 만들어보는 분들도 어렵지 않게 완성할 수 있답니다. </b></span><span class=\"se-fs-fs19 se-ff-nanumsquare\" id=\"SE-78db06c8-cee6-4a54-8fea-c4ab6eb52600\" style=\"color:#000000;\">사진을 올리고 템플릿만 적용하면 큰 수정 없이도 포토북이 자연스럽게 구성할 수 있는데요. </span></p><!-- } SE-TEXT --><!-- SE-TEXT { --><p class=\"se-text-paragraph se-text-paragraph-align-justify\" id=\"SE-f1e9f8f4-46a5-4568-97ef-3f13982b024d\" style=\"line-height:1.9;\"><span class=\"se-fs-fs19 se-ff-nanumsquare\" id=\"SE-308fc9ae-8ccf-42c8-a0c3-0d6c39efcc46\" style=\"color:#000000;\">​</span></p><!-- } SE-TEXT --><!-- SE-TEXT { --><p class=\"se-text-paragraph se-text-paragraph-align-justify\" id=\"SE-579e1817-6897-4aff-af78-4451a83a090f\" style=\"line-height:1.9;\"><span class=\"se-fs-fs19 se-ff-nanumsquare\" id=\"SE-b0e9a435-38a2-4a7f-b910-58cfa76110b3\" style=\"color:#000000;background-color:#b0f1ff;\"><b>인쇄 전에는 전문 오퍼레이터가 색감 체크와 보정까지 직접 진행하기 때문에 결과물의 퀄리티가 다르답니다.</b></span><span class=\"se-fs-fs19 se-ff-nanumsquare\" id=\"SE-e8e9f449-764c-40ab-ad4e-955446991eb8\" style=\"color:#000000;\"> 받아보면 “생각보다 훨씬 잘 나왔다\"라는 말이 먼저 나오는 이유입니다. </span><span class=\"se-fs-fs19 se-ff-nanumsquare\" id=\"SE-763df225-22a6-460d-ae10-b7c58f9917e1\" style=\"color:#000000;\"><b>제작이 완료되면 각각 단계별 전문가들이 제작을 진행하게 되는데요. 사진 출력, 표지 코팅, 표지 코팅 후 합치기, 내지 코팅, 성책 이렇게 5단계로 진행된답니다.</b></span></p><!-- } SE-TEXT --><!-- SE-TEXT { --><p class=\"se-text-paragraph se-text-paragraph-align-justify\" id=\"SE-bdd82c1a-cb72-4465-8d8e-76e7730229f9\" style=\"line-height:1.9;\"><span class=\"se-fs-fs19 se-ff-nanumsquare\" id=\"SE-755917a1-0c67-482e-a148-9d674757bcf0\" style=\"color:#000000;\">​</span></p><!-- } SE-TEXT -->\n</div>\n</div>\n</div>\n\n</div> <div class=\"se-component se-video se-l-default\">\n<div class=\"se-component-content se-component-content-fit\">\n<div class=\"se-section se-section-video se-section-align-center se-l-default\">\n<div class=\"se-module se-module-video\" id=\"SE-0068a470-b088-4f7d-8941-845b5d7ef3c5\">\n</div>\n</div>\n</div>\n\n</div> <div class=\"se-component se-text se-l-default\" id=\"SE-e53e759d-0d26-4b17-b861-97d55a91d075\">\n<div class=\"se-component-content\">\n<div class=\"se-section se-section-text se-l-default\">\n<div class=\"se-module se-module-text\">\n<!-- SE-TEXT { --><p class=\"se-text-paragraph se-text-paragraph-align-justify\" id=\"SE-a07a5467-b4d0-48ac-9366-d0a4c3944aa6\" style=\"line-height:1.9;\"><span class=\"se-fs-fs19 se-ff-nanumsquare\" id=\"SE-1a43af7c-9d62-49d0-8b69-f8e4eea5e539\" style=\"color:#000000;\">​</span></p><!-- } SE-TEXT -->\n</div>\n</div>\n</div>\n\n</div> <div class=\"se-component se-image se-l-default\" id=\"SE-2c03e3ca-725c-4ff4-8a4e-3ed88ba3405f\">\n<div class=\"se-component-content se-component-content-fit\">\n<div class=\"se-section se-section-image se-l-default se-section-align-justify\">\n<div class=\"se-module se-module-image\" style=\"\">\n<a class=\"se-module-image-link __se_image_link __se_link\" data-linkdata='{\"id\" : \"SE-2c03e3ca-725c-4ff4-8a4e-3ed88ba3405f\", \"src\" : \"https://mblogthumb-phinf.pstatic.net/MjAyNTA1MjNfNiAg/MDAxNzQ3OTk0NTQ1MDEw.XRGZTY8ZmO_bpxQSnGjXDffmKrAoJGRh_FxA3cZ7gp4g.XWFWQa88PMW4vRiwPwIqretvsybyc9F6DHFp3fnBsBQg.PNG/014.png\", \"originalWidth\" : \"1080\", \"originalHeight\" : \"1080\", \"linkUse\" : \"false\", \"link\" : \"\"}' data-linktype=\"img\" href=\"#\" onclick=\"return false;\" style=\"\">\n<img alt=\"\" class=\"se-image-resource\" src=\"https://mblogthumb-phinf.pstatic.net/MjAyNTA1MjNfNiAg/MDAxNzQ3OTk0NTQ1MDEw.XRGZTY8ZmO_bpxQSnGjXDffmKrAoJGRh_FxA3cZ7gp4g.XWFWQa88PMW4vRiwPwIqretvsybyc9F6DHFp3fnBsBQg.PNG/014.png?type=w966\"/>\n</a>\n</div>\n</div>\n</div>\n\n</div>\n<div class=\"se-component se-text se-l-default\" id=\"SE-9d5c664f-941c-4854-9b7a-509e2a777d5a\">\n<div class=\"se-component-content\">\n<div class=\"se-section se-section-text se-l-default\">\n<div class=\"se-module se-module-text\">\n<!-- SE-TEXT { --><p class=\"se-text-paragraph se-text-paragraph-align-justify\" id=\"SE-657ad85f-e236-47c5-b170-b65dffd5e6bf\" style=\"line-height:1.9;\"><span class=\"se-fs-fs19 se-ff-nanumsquare\" id=\"SE-b0d828d9-0a0b-48a6-95ae-a93da431e7fd\" style=\"color:#000000;\"> </span></p><!-- } SE-TEXT --><!-- SE-TEXT { --><p class=\"se-text-paragraph se-text-paragraph-align-justify\" id=\"SE-eb48eb4b-7b57-4bc9-8d2f-a50d8de81e35\" style=\"line-height:1.9;\"><span class=\"se-fs-fs19 se-ff-nanumsquare\" id=\"SE-164e0a65-1706-4e49-9901-da71f0b81824\" style=\"color:#000000;\">지금 사진 정리를 미루고 계신다면, 이번 여름 홋카이도 여행부터는 제대로 남겨보세요. 보기 좋고 오래 두고 싶은 포토북, 점보포토에서 간편하게 시작해 보세요.</span></p><!-- } SE-TEXT --><!-- SE-TEXT { --><p class=\"se-text-paragraph se-text-paragraph-align-justify\" id=\"SE-cb697a72-c1c5-47ca-b1cb-20653ae518b2\" style=\"line-height:1.9;\"><span class=\"se-fs-fs19 se-ff-nanumsquare\" id=\"SE-c73bb616-f20b-4ee7-906b-7c02497d8c99\" style=\"color:#000000;\"> </span></p><!-- } SE-TEXT -->\n</div>\n</div>\n</div>\n\n</div> <div class=\"se-component se-video se-l-default\">\n<div class=\"se-component-content se-component-content-fit\">\n<div class=\"se-section se-section-video se-section-align-justify se-l-default\">\n<div class=\"se-module se-module-video\" id=\"SE-5a2fce57-99fb-4fb5-9ac1-bc82b926d6f5\">\n</div>\n</div>\n</div>\n\n</div> <div class=\"se-component se-text se-l-default\" id=\"SE-c126c816-9a4e-460f-a3bc-fc4b3abd2d5a\">\n<div class=\"se-component-content\">\n<div class=\"se-section se-section-text se-l-default\">\n<div class=\"se-module se-module-text\">\n<!-- SE-TEXT { --><p class=\"se-text-paragraph se-text-paragraph-align-justify\" id=\"SE-5ab260e7-fa42-4c67-8679-66ac0f09d21b\" style=\"line-height:1.9;\"><span class=\"se-fs-fs19 se-ff-nanumsquare\" id=\"SE-41d89560-efa3-4611-9893-0b6c60c7e23b\" style=\"color:#000000;\">​</span></p><!-- } SE-TEXT -->\n</div>\n</div>\n</div>\n\n</div>",
  "media": [
    {
      "url": "https://storep-phinf.pstatic.net/motion2d_01/original_7.png?type=p100_100",
      "kind": "img"
    },
    {
      "url": "https://mblogthumb-phinf.pstatic.net/MjAyNTA1MjNfMTM2/MDAxNzQ3OTk0NDY4MjEz.XVNjwHvSR2Wr8AMLlT-bC7FEIZ6iLcxMh-TPtDZBRrcg.cNQhuleUYvqeTCHt2TytQBj2ULMGQOEuWZp2saNPEn0g.PNG/001.png?type=w966",
      "kind": "img"
    },
    {
      "url": "https://mblogthumb-phinf.pstatic.net/MjAyNTA1MjNfNTYg/MDAxNzQ3OTk0NTA2MzU4.Mlty0tk1HnghKfCeFIFUnhvEE55zzJey6r4ghtNDeBgg.35irNVUkegraLp4KN1DBITVNNNvO3MDzjnm-JjAqlLkg.PNG/002.png?type=w966",
      "kind": "img"
    },
    {
      "url": "https://mblogthumb-phinf.pstatic.net/MjAyNTA1MjNfMjIz/MDAxNzQ3OTk0NTA5MTk0.hdoY3ehEs8BbEm1w3vDITW8odbRIWPGMQv9K3GDIh4Qg.9_YFbJfkLukWmP-am9mhKINQFblcxeina9fVpdXkwvAg.PNG/003.png?type=w966",
      "kind": "img"
    },
    {
      "url": "https://mblogthumb-phinf.pstatic.net/MjAyNTA1MjNfNjEg/MDAxNzQ3OTk0NTEyNTY1.8Ivg9MAkz45IC4NzvgmKbaSh0GmmVppa4YoN1eFjWSQg.rnIYxfrqBBqmzze4PCeq56uglmTiJeNHfJOGmxblHT4g.PNG/004.png?type=w966",
      "kind": "img"
    },
    {
      "url": "https://mblogthumb-phinf.pstatic.net/MjAyNTA1MjNfMzUg/MDAxNzQ3OTk0NTE3ODk4.9xvPv-NPK5_Q6_kWyYtClT2Y2kgsCfcJ1eaMu5SLD_Eg.ISq-vWIup8kCoCwmlV4xdGqlPGCy_6_8SkR5bK5baAsg.PNG/005.png?type=w966",
      "kind": "img"
    },
    {
      "url": "https://mblogthumb-phinf.pstatic.net/MjAyNTA1MjNfMjQ3/MDAxNzQ3OTk0NTIxMTQw.oQKCeSQY7w3gu72q-jdfgF4IBhSqkMWbn2yKbXCDTokg.tOkG5LekzeLjCSChVib7Y0-LQHuOjRj3Ovx-n-YFRzsg.PNG/006.png?type=w966",
      "kind": "img"
    },
    {
      "url": "https://mblogthumb-phinf.pstatic.net/MjAyNTA1MjNfMTUy/MDAxNzQ3OTk0NTIzNDU3.9aBkp46Mfk8eOog1hTAHPMR2roLtFSSmA-ZUO67zehwg.-xauF1-Eae1xzTPVkkZE5HUX70NEEErqhXe_8XWXeVEg.PNG/007.png?type=w966",
      "kind": "img"
    },
    {
      "url": "https://mblogthumb-phinf.pstatic.net/MjAyNTA1MjNfOTkg/MDAxNzQ3OTk0NTI2MjEy.m-WRtW5gRCX1gtbAWr9xE5r9imaUEoHHiZOKyt1Pdz0g.y161yp5lWnZXbeyjjRPNwnl-YRWlACBgKILmlr0AUVcg.PNG/008.png?type=w966",
      "kind": "img"
    },
    {
      "url": "https://mblogthumb-phinf.pstatic.net/MjAyNTA1MjNfNDcg/MDAxNzQ3OTk0NTI4NzYx.HWDVbdOcnuMfR9vipoBXgXr6zU--FZb4F8fTqleZC_Ig.WUQor7-a6edVfJJb8IlvHjBd8RIxAegr5T8dQtCsYv4g.PNG/009.png?type=w966",
      "kind": "img"
    },
    {
      "url": "https://mblogthumb-phinf.pstatic.net/MjAyNTA1MjNfMjg4/MDAxNzQ3OTk0NTMxMjA1.IQ-EJpw8klHVR67n5mqr1wiPDHKVkebTHyqkTFS8BpEg.RljPfc4CrDmiiur_KU1fVOkM0FPMyQ3ioU2F7Pzew1kg.PNG/010.png?type=w966",
      "kind": "img"
    },
    {
      "url": "https://mblogthumb-phinf.pstatic.net/MjAyNTA1MjNfMTQg/MDAxNzQ3OTk0NTMzODg1.MREzKk5qreRL_sAGVZQOxhsSNPUxwSIxa74EJeSTxWog.TLbmOiRQI8_M6lRyMYS71WOr6Fzh0C4ekVOc2cSCd6gg.PNG/011.png?type=w966",
      "kind": "img"
    },
    {
      "url": "https://mblogthumb-phinf.pstatic.net/MjAyNTA1MjNfNzQg/MDAxNzQ3OTk0NTM2MTcz.1v_J6ccN96LhvlOQvN9HM0G5t7Vd64RWWJB5_sT6OGEg.ZHHahLNwGrQhe7gO_LnrmC29LYwh2HtbyNxpCijVZTkg.PNG/012.png?type=w966",
      "kind": "img"
    },
    {
      "url": "https://mblogthumb-phinf.pstatic.net/MjAyNTA1MjNfNDAg/MDAxNzQ3OTk0NTM4NjEy.hBHQMlOvaW3t8SHpicFUqIQuZAHOLAcZFLvdcKjkL8wg.TtixAwQpF90MB5Uc_CWuFi3yHVKCOzYnbZ0ffUfbggcg.PNG/013.png?type=w966",
      "kind": "img"
    },
    {
      "url": "https://mblogthumb-phinf.pstatic.net/MjAyNTA1MjNfNiAg/MDAxNzQ3OTk0NTQ1MDEw.XRGZTY8ZmO_bpxQSnGjXDffmKrAoJGRh_FxA3cZ7gp4g.XWFWQa88PMW4vRiwPwIqretvsybyc9F6DHFp3fnBsBQg.PNG/014.png?type=w966",
      "kind": "img"
    }
  ],
  "images": [
    "https://storep-phinf.pstatic.net/motion2d_01/original_7.png?type=p100_100",
    "https://mblogthumb-phinf.pstatic.net/MjAyNTA1MjNfMTM2/MDAxNzQ3OTk0NDY4MjEz.XVNjwHvSR2Wr8AMLlT-bC7FEIZ6iLcxMh-TPtDZBRrcg.cNQhuleUYvqeTCHt2TytQBj2ULMGQOEuWZp2saNPEn0g.PNG/001.png?type=w966",
    "https://mblogthumb-phinf.pstatic.net/MjAyNTA1MjNfNTYg/MDAxNzQ3OTk0NTA2MzU4.Mlty0tk1HnghKfCeFIFUnhvEE55zzJey6r4ghtNDeBgg.35irNVUkegraLp4KN1DBITVNNNvO3MDzjnm-JjAqlLkg.PNG/002.png?type=w966",
    "https://mblogthumb-phinf.pstatic.net/MjAyNTA1MjNfMjIz/MDAxNzQ3OTk0NTA5MTk0.hdoY3ehEs8BbEm1w3vDITW8odbRIWPGMQv9K3GDIh4Qg.9_YFbJfkLukWmP-am9mhKINQFblcxeina9fVpdXkwvAg.PNG/003.png?type=w966",
    "https://mblogthumb-phinf.pstatic.net/MjAyNTA1MjNfNjEg/MDAxNzQ3OTk0NTEyNTY1.8Ivg9MAkz45IC4NzvgmKbaSh0GmmVppa4YoN1eFjWSQg.rnIYxfrqBBqmzze4PCeq56uglmTiJeNHfJOGmxblHT4g.PNG/004.png?type=w966",
    "https://mblogthumb-phinf.pstatic.net/MjAyNTA1MjNfMzUg/MDAxNzQ3OTk0NTE3ODk4.9xvPv-NPK5_Q6_kWyYtClT2Y2kgsCfcJ1eaMu5SLD_Eg.ISq-vWIup8kCoCwmlV4xdGqlPGCy_6_8SkR5bK5baAsg.PNG/005.png?type=w966",
    "https://mblogthumb-phinf.pstatic.net/MjAyNTA1MjNfMjQ3/MDAxNzQ3OTk0NTIxMTQw.oQKCeSQY7w3gu72q-jdfgF4IBhSqkMWbn2yKbXCDTokg.tOkG5LekzeLjCSChVib7Y0-LQHuOjRj3Ovx-n-YFRzsg.PNG/006.png?type=w966",
    "https://mblogthumb-phinf.pstatic.net/MjAyNTA1MjNfMTUy/MDAxNzQ3OTk0NTIzNDU3.9aBkp46Mfk8eOog1hTAHPMR2roLtFSSmA-ZUO67zehwg.-xauF1-Eae1xzTPVkkZE5HUX70NEEErqhXe_8XWXeVEg.PNG/007.png?type=w966",
    "https://mblogthumb-phinf.pstatic.net/MjAyNTA1MjNfOTkg/MDAxNzQ3OTk0NTI2MjEy.m-WRtW5gRCX1gtbAWr9xE5r9imaUEoHHiZOKyt1Pdz0g.y161yp5lWnZXbeyjjRPNwnl-YRWlACBgKILmlr0AUVcg.PNG/008.png?type=w966",
    "https://mblogthumb-phinf.pstatic.net/MjAyNTA1MjNfNDcg/MDAxNzQ3OTk0NTI4NzYx.HWDVbdOcnuMfR9vipoBXgXr6zU--FZb4F8fTqleZC_Ig.WUQor7-a6edVfJJb8IlvHjBd8RIxAegr5T8dQtCsYv4g.PNG/009.png?type=w966",
    "https://mblogthumb-phinf.pstatic.net/MjAyNTA1MjNfMjg4/MDAxNzQ3OTk0NTMxMjA1.IQ-EJpw8klHVR67n5mqr1wiPDHKVkebTHyqkTFS8BpEg.RljPfc4CrDmiiur_KU1fVOkM0FPMyQ3ioU2F7Pzew1kg.PNG/010.png?type=w966",
    "https://mblogthumb-phinf.pstatic.net/MjAyNTA1MjNfMTQg/MDAxNzQ3OTk0NTMzODg1.MREzKk5qreRL_sAGVZQOxhsSNPUxwSIxa74EJeSTxWog.TLbmOiRQI8_M6lRyMYS71WOr6Fzh0C4ekVOc2cSCd6gg.PNG/011.png?type=w966",
    "https://mblogthumb-phinf.pstatic.net/MjAyNTA1MjNfNzQg/MDAxNzQ3OTk0NTM2MTcz.1v_J6ccN96LhvlOQvN9HM0G5t7Vd64RWWJB5_sT6OGEg.ZHHahLNwGrQhe7gO_LnrmC29LYwh2HtbyNxpCijVZTkg.PNG/012.png?type=w966",
    "https://mblogthumb-phinf.pstatic.net/MjAyNTA1MjNfNDAg/MDAxNzQ3OTk0NTM4NjEy.hBHQMlOvaW3t8SHpicFUqIQuZAHOLAcZFLvdcKjkL8wg.TtixAwQpF90MB5Uc_CWuFi3yHVKCOzYnbZ0ffUfbggcg.PNG/013.png?type=w966",
    "https://mblogthumb-phinf.pstatic.net/MjAyNTA1MjNfNiAg/MDAxNzQ3OTk0NTQ1MDEw.XRGZTY8ZmO_bpxQSnGjXDffmKrAoJGRh_FxA3cZ7gp4g.XWFWQa88PMW4vRiwPwIqretvsybyc9F6DHFp3fnBsBQg.PNG/014.png?type=w966"
  ],
  "date": "2025-05-23",
  "addDate": "2025. 5. 23.",
  "categoryNo": "28",
  "image_local": {
    "https://storep-phinf.pstatic.net/motion2d_01/original_7.png?type=p100_100": "data/images/223875626500/000.png",
    "https://mblogthumb-phinf.pstatic.net/MjAyNTA1MjNfMTM2/MDAxNzQ3OTk0NDY4MjEz.XVNjwHvSR2Wr8AMLlT-bC7FEIZ6iLcxMh-TPtDZBRrcg.cNQhuleUYvqeTCHt2TytQBj2ULMGQOEuWZp2saNPEn0g.PNG/001.png?type=w966": "data/images/223875626500/001.png",
    "https://mblogthumb-phinf.pstatic.net/MjAyNTA1MjNfNTYg/MDAxNzQ3OTk0NTA2MzU4.Mlty0tk1HnghKfCeFIFUnhvEE55zzJey6r4ghtNDeBgg.35irNVUkegraLp4KN1DBITVNNNvO3MDzjnm-JjAqlLkg.PNG/002.png?type=w966": "data/images/223875626500/002.png",
    "https://mblogthumb-phinf.pstatic.net/MjAyNTA1MjNfMjIz/MDAxNzQ3OTk0NTA5MTk0.hdoY3ehEs8BbEm1w3vDITW8odbRIWPGMQv9K3GDIh4Qg.9_YFbJfkLukWmP-am9mhKINQFblcxeina9fVpdXkwvAg.PNG/003.png?type=w966": "data/images/223875626500/003.png",
    "https://mblogthumb-phinf.pstatic.net/MjAyNTA1MjNfNjEg/MDAxNzQ3OTk0NTEyNTY1.8Ivg9MAkz45IC4NzvgmKbaSh0GmmVppa4YoN1eFjWSQg.rnIYxfrqBBqmzze4PCeq56uglmTiJeNHfJOGmxblHT4g.PNG/004.png?type=w966": "data/images/223875626500/004.png",
    "https://mblogthumb-phinf.pstatic.net/MjAyNTA1MjNfMzUg/MDAxNzQ3OTk0NTE3ODk4.9xvPv-NPK5_Q6_kWyYtClT2Y2kgsCfcJ1eaMu5SLD_Eg.ISq-vWIup8kCoCwmlV4xdGqlPGCy_6_8SkR5bK5baAsg.PNG/005.png?type=w966": "data/images/223875626500/005.png",
    "https://mblogthumb-phinf.pstatic.net/MjAyNTA1MjNfMjQ3/MDAxNzQ3OTk0NTIxMTQw.oQKCeSQY7w3gu72q-jdfgF4IBhSqkMWbn2yKbXCDTokg.tOkG5LekzeLjCSChVib7Y0-LQHuOjRj3Ovx-n-YFRzsg.PNG/006.png?type=w966": "data/images/223875626500/006.png",
    "https://mblogthumb-phinf.pstatic.net/MjAyNTA1MjNfMTUy/MDAxNzQ3OTk0NTIzNDU3.9aBkp46Mfk8eOog1hTAHPMR2roLtFSSmA-ZUO67zehwg.-xauF1-Eae1xzTPVkkZE5HUX70NEEErqhXe_8XWXeVEg.PNG/007.png?type=w966": "data/images/223875626500/007.png",
    "https://mblogthumb-phinf.pstatic.net/MjAyNTA1MjNfOTkg/MDAxNzQ3OTk0NTI2MjEy.m-WRtW5gRCX1gtbAWr9xE5r9imaUEoHHiZOKyt1Pdz0g.y161yp5lWnZXbeyjjRPNwnl-YRWlACBgKILmlr0AUVcg.PNG/008.png?type=w966": "data/images/223875626500/008.png",
    "https://mblogthumb-phinf.pstatic.net/MjAyNTA1MjNfNDcg/MDAxNzQ3OTk0NTI4NzYx.HWDVbdOcnuMfR9vipoBXgXr6zU--FZb4F8fTqleZC_Ig.WUQor7-a6edVfJJb8IlvHjBd8RIxAegr5T8dQtCsYv4g.PNG/009.png?type=w966": "data/images/223875626500/009.png",
    "https://mblogthumb-phinf.pstatic.net/MjAyNTA1MjNfMjg4/MDAxNzQ3OTk0NTMxMjA1.IQ-EJpw8klHVR67n5mqr1wiPDHKVkebTHyqkTFS8BpEg.RljPfc4CrDmiiur_KU1fVOkM0FPMyQ3ioU2F7Pzew1kg.PNG/010.png?type=w966": "data/images/223875626500/010.png",
    "https://mblogthumb-phinf.pstatic.net/MjAyNTA1MjNfMTQg/MDAxNzQ3OTk0NTMzODg1.MREzKk5qreRL_sAGVZQOxhsSNPUxwSIxa74EJeSTxWog.TLbmOiRQI8_M6lRyMYS71WOr6Fzh0C4ekVOc2cSCd6gg.PNG/011.png?type=w966": "data/images/223875626500/011.png",
    "https://mblogthumb-phinf.pstatic.net/MjAyNTA1MjNfNzQg/MDAxNzQ3OTk0NTM2MTcz.1v_J6ccN96LhvlOQvN9HM0G5t7Vd64RWWJB5_sT6OGEg.ZHHahLNwGrQhe7gO_LnrmC29LYwh2HtbyNxpCijVZTkg.PNG/012.png?type=w966": "data/images/223875626500/012.png",
    "https://mblogthumb-phinf.pstatic.net/MjAyNTA1MjNfNDAg/MDAxNzQ3OTk0NTM4NjEy.hBHQMlOvaW3t8SHpicFUqIQuZAHOLAcZFLvdcKjkL8wg.TtixAwQpF90MB5Uc_CWuFi3yHVKCOzYnbZ0ffUfbggcg.PNG/013.png?type=w966": "data/images/223875626500/013.png",
    "https://mblogthumb-phinf.pstatic.net/MjAyNTA1MjNfNiAg/MDAxNzQ3OTk0NTQ1MDEw.XRGZTY8ZmO_bpxQSnGjXDffmKrAoJGRh_FxA3cZ7gp4g.XWFWQa88PMW4vRiwPwIqretvsybyc9F6DHFp3fnBsBQg.PNG/014.png?type=w966": "data/images/223875626500/014.png"
  }
}